{
  "date": "2025-04-24",
  "projects": {
    "Back-end": {
      "totalLinesAdded": 205,
      "totalLinesRemoved": 3,
      "totalActiveTime": 2,
      "files": {
        "c:\\Users\\ludov\\Documents\\Code\\C#\\Projet-integration\\Back-end\\Backend\\Program.cs": [
          {
            "timestamp": "2025-04-24T16:32:34.227Z",
            "fileName": "c:\\Users\\ludov\\Documents\\Code\\C#\\Projet-integration\\Back-end\\Backend\\Program.cs",
            "fileType": ".cs",
            "linesAdded": 202,
            "linesRemoved": 0,
            "projectName": "Back-end",
            "content": {
              "added": [],
              "removed": []
            },
            "duration": 0,
            "language": "cs"
          },
          {
            "timestamp": "2025-04-24T16:32:35.610Z",
            "fileName": "c:\\Users\\ludov\\Documents\\Code\\C#\\Projet-integration\\Back-end\\Backend\\Program.cs",
            "fileType": ".cs",
            "linesAdded": 3,
            "linesRemoved": 0,
            "projectName": "Back-end",
            "content": {
              "added": [],
              "removed": []
            },
            "duration": 1,
            "language": "cs"
          },
          {
            "timestamp": "2025-04-24T16:33:15.471Z",
            "fileName": "c:\\Users\\ludov\\Documents\\Code\\C#\\Projet-integration\\Back-end\\Backend\\Program.cs",
            "fileType": ".cs",
            "linesAdded": 0,
            "linesRemoved": 3,
            "projectName": "Back-end",
            "content": {
              "added": [],
              "removed": []
            },
            "duration": 1,
            "language": "cs"
          }
        ]
      },
      "languageStats": {
        "cs": 2
      },
      "changeFrequency": {
        "18": 2
      },
      "topFiles": [
        "c:\\Users\\ludov\\Documents\\Code\\C#\\Projet-integration\\Back-end\\Backend\\Program.cs"
      ],
      "averageChangeSize": 69.33333333333333
    }
  },
  "totalActiveTime": 2,
  "totalProjects": 1,
  "totalFiles": 1,
  "mostActiveHours": [
    18
  ],
  "mostUsedLanguages": [
    "cs"
  ]
}