{
  "date": "2025-10-21",
  "projects": {
    "SkinTrack": {
      "totalLinesAdded": 579,
      "totalLinesRemoved": 123,
      "totalActiveTime": 100,
      "files": {
        "c:\\Users\\ludov\\Documents\\Code\\C#\\SkinTrack\\SkinTrack\\Views\\CarsView.axaml": [
          {
            "timestamp": "2025-10-21T15:54:12.735Z",
            "fileName": "c:\\Users\\ludov\\Documents\\Code\\C#\\SkinTrack\\SkinTrack\\Views\\CarsView.axaml",
            "fileType": ".axaml",
            "linesAdded": 9,
            "linesRemoved": 0,
            "projectName": "SkinTrack",
            "content": {
              "added": [],
              "removed": []
            },
            "duration": 0,
            "language": "axaml"
          },
          {
            "timestamp": "2025-10-21T15:54:13.760Z",
            "fileName": "c:\\Users\\ludov\\Documents\\Code\\C#\\SkinTrack\\SkinTrack\\Views\\CarsView.axaml",
            "fileType": ".axaml",
            "linesAdded": 6,
            "linesRemoved": 0,
            "projectName": "SkinTrack",
            "content": {
              "added": [],
              "removed": []
            },
            "duration": 1,
            "language": "axaml"
          },
          {
            "timestamp": "2025-10-21T17:33:02.839Z",
            "fileName": "c:\\Users\\ludov\\Documents\\Code\\C#\\SkinTrack\\SkinTrack\\Views\\CarsView.axaml",
            "fileType": ".axaml",
            "linesAdded": 15,
            "linesRemoved": 0,
            "projectName": "SkinTrack",
            "content": {
              "added": [],
              "removed": []
            },
            "duration": 0,
            "language": "axaml"
          },
          {
            "timestamp": "2025-10-21T17:34:03.590Z",
            "fileName": "c:\\Users\\ludov\\Documents\\Code\\C#\\SkinTrack\\SkinTrack\\Views\\CarsView.axaml",
            "fileType": ".axaml",
            "linesAdded": 0,
            "linesRemoved": 1,
            "projectName": "SkinTrack",
            "content": {
              "added": [],
              "removed": []
            },
            "duration": 2,
            "language": "axaml"
          },
          {
            "timestamp": "2025-10-21T17:34:06.268Z",
            "fileName": "c:\\Users\\ludov\\Documents\\Code\\C#\\SkinTrack\\SkinTrack\\Views\\CarsView.axaml",
            "fileType": ".axaml",
            "linesAdded": 0,
            "linesRemoved": 1,
            "projectName": "SkinTrack",
            "content": {
              "added": [],
              "removed": []
            },
            "duration": 1,
            "language": "axaml"
          },
          {
            "timestamp": "2025-10-21T18:11:26.002Z",
            "fileName": "c:\\Users\\ludov\\Documents\\Code\\C#\\SkinTrack\\SkinTrack\\Views\\CarsView.axaml",
            "fileType": ".axaml",
            "linesAdded": 13,
            "linesRemoved": 0,
            "projectName": "SkinTrack",
            "content": {
              "added": [],
              "removed": []
            },
            "duration": 1,
            "language": "axaml"
          },
          {
            "timestamp": "2025-10-21T18:11:27.015Z",
            "fileName": "c:\\Users\\ludov\\Documents\\Code\\C#\\SkinTrack\\SkinTrack\\Views\\CarsView.axaml",
            "fileType": ".axaml",
            "linesAdded": 15,
            "linesRemoved": 0,
            "projectName": "SkinTrack",
            "content": {
              "added": [],
              "removed": []
            },
            "duration": 1,
            "language": "axaml"
          },
          {
            "timestamp": "2025-10-21T18:11:30.722Z",
            "fileName": "c:\\Users\\ludov\\Documents\\Code\\C#\\SkinTrack\\SkinTrack\\Views\\CarsView.axaml",
            "fileType": ".axaml",
            "linesAdded": 0,
            "linesRemoved": 15,
            "projectName": "SkinTrack",
            "content": {
              "added": [],
              "removed": []
            },
            "duration": 1,
            "language": "axaml"
          },
          {
            "timestamp": "2025-10-21T18:11:33.025Z",
            "fileName": "c:\\Users\\ludov\\Documents\\Code\\C#\\SkinTrack\\SkinTrack\\Views\\CarsView.axaml",
            "fileType": ".axaml",
            "linesAdded": 15,
            "linesRemoved": 0,
            "projectName": "SkinTrack",
            "content": {
              "added": [],
              "removed": []
            },
            "duration": 1,
            "language": "axaml"
          },
          {
            "timestamp": "2025-10-21T18:11:34.391Z",
            "fileName": "c:\\Users\\ludov\\Documents\\Code\\C#\\SkinTrack\\SkinTrack\\Views\\CarsView.axaml",
            "fileType": ".axaml",
            "linesAdded": 0,
            "linesRemoved": 15,
            "projectName": "SkinTrack",
            "content": {
              "added": [],
              "removed": []
            },
            "duration": 1,
            "language": "axaml"
          },
          {
            "timestamp": "2025-10-21T18:11:47.884Z",
            "fileName": "c:\\Users\\ludov\\Documents\\Code\\C#\\SkinTrack\\SkinTrack\\Views\\CarsView.axaml",
            "fileType": ".axaml",
            "linesAdded": 15,
            "linesRemoved": 0,
            "projectName": "SkinTrack",
            "content": {
              "added": [],
              "removed": []
            },
            "duration": 1,
            "language": "axaml"
          },
          {
            "timestamp": "2025-10-21T18:42:19.267Z",
            "fileName": "c:\\Users\\ludov\\Documents\\Code\\C#\\SkinTrack\\SkinTrack\\Views\\CarsView.axaml",
            "fileType": ".axaml",
            "linesAdded": 28,
            "linesRemoved": 0,
            "projectName": "SkinTrack",
            "content": {
              "added": [],
              "removed": []
            },
            "duration": 0,
            "language": "axaml"
          },
          {
            "timestamp": "2025-10-21T18:42:20.287Z",
            "fileName": "c:\\Users\\ludov\\Documents\\Code\\C#\\SkinTrack\\SkinTrack\\Views\\CarsView.axaml",
            "fileType": ".axaml",
            "linesAdded": 1,
            "linesRemoved": 0,
            "projectName": "SkinTrack",
            "content": {
              "added": [],
              "removed": []
            },
            "duration": 1,
            "language": "axaml"
          },
          {
            "timestamp": "2025-10-21T18:44:05.262Z",
            "fileName": "c:\\Users\\ludov\\Documents\\Code\\C#\\SkinTrack\\SkinTrack\\Views\\CarsView.axaml",
            "fileType": ".axaml",
            "linesAdded": 1,
            "linesRemoved": 0,
            "projectName": "SkinTrack",
            "content": {
              "added": [],
              "removed": []
            },
            "duration": 2,
            "language": "axaml"
          },
          {
            "timestamp": "2025-10-21T18:44:13.288Z",
            "fileName": "c:\\Users\\ludov\\Documents\\Code\\C#\\SkinTrack\\SkinTrack\\Views\\CarsView.axaml",
            "fileType": ".axaml",
            "linesAdded": 0,
            "linesRemoved": 1,
            "projectName": "SkinTrack",
            "content": {
              "added": [],
              "removed": []
            },
            "duration": 1,
            "language": "axaml"
          },
          {
            "timestamp": "2025-10-21T18:45:11.844Z",
            "fileName": "c:\\Users\\ludov\\Documents\\Code\\C#\\SkinTrack\\SkinTrack\\Views\\CarsView.axaml",
            "fileType": ".axaml",
            "linesAdded": 1,
            "linesRemoved": 0,
            "projectName": "SkinTrack",
            "content": {
              "added": [],
              "removed": []
            },
            "duration": 1,
            "language": "axaml"
          },
          {
            "timestamp": "2025-10-21T18:45:53.532Z",
            "fileName": "c:\\Users\\ludov\\Documents\\Code\\C#\\SkinTrack\\SkinTrack\\Views\\CarsView.axaml",
            "fileType": ".axaml",
            "linesAdded": 1,
            "linesRemoved": 0,
            "projectName": "SkinTrack",
            "content": {
              "added": [],
              "removed": []
            },
            "duration": 1,
            "language": "axaml"
          },
          {
            "timestamp": "2025-10-21T18:46:10.440Z",
            "fileName": "c:\\Users\\ludov\\Documents\\Code\\C#\\SkinTrack\\SkinTrack\\Views\\CarsView.axaml",
            "fileType": ".axaml",
            "linesAdded": 1,
            "linesRemoved": 0,
            "projectName": "SkinTrack",
            "content": {
              "added": [],
              "removed": []
            },
            "duration": 1,
            "language": "axaml"
          },
          {
            "timestamp": "2025-10-21T18:46:17.203Z",
            "fileName": "c:\\Users\\ludov\\Documents\\Code\\C#\\SkinTrack\\SkinTrack\\Views\\CarsView.axaml",
            "fileType": ".axaml",
            "linesAdded": 1,
            "linesRemoved": 0,
            "projectName": "SkinTrack",
            "content": {
              "added": [],
              "removed": []
            },
            "duration": 1,
            "language": "axaml"
          },
          {
            "timestamp": "2025-10-21T18:46:39.571Z",
            "fileName": "c:\\Users\\ludov\\Documents\\Code\\C#\\SkinTrack\\SkinTrack\\Views\\CarsView.axaml",
            "fileType": ".axaml",
            "linesAdded": 1,
            "linesRemoved": 0,
            "projectName": "SkinTrack",
            "content": {
              "added": [],
              "removed": []
            },
            "duration": 1,
            "language": "axaml"
          },
          {
            "timestamp": "2025-10-21T18:47:13.571Z",
            "fileName": "c:\\Users\\ludov\\Documents\\Code\\C#\\SkinTrack\\SkinTrack\\Views\\CarsView.axaml",
            "fileType": ".axaml",
            "linesAdded": 1,
            "linesRemoved": 0,
            "projectName": "SkinTrack",
            "content": {
              "added": [],
              "removed": []
            },
            "duration": 1,
            "language": "axaml"
          },
          {
            "timestamp": "2025-10-21T18:47:19.021Z",
            "fileName": "c:\\Users\\ludov\\Documents\\Code\\C#\\SkinTrack\\SkinTrack\\Views\\CarsView.axaml",
            "fileType": ".axaml",
            "linesAdded": 0,
            "linesRemoved": 2,
            "projectName": "SkinTrack",
            "content": {
              "added": [],
              "removed": []
            },
            "duration": 1,
            "language": "axaml"
          },
          {
            "timestamp": "2025-10-21T18:48:09.214Z",
            "fileName": "c:\\Users\\ludov\\Documents\\Code\\C#\\SkinTrack\\SkinTrack\\Views\\CarsView.axaml",
            "fileType": ".axaml",
            "linesAdded": 5,
            "linesRemoved": 0,
            "projectName": "SkinTrack",
            "content": {
              "added": [],
              "removed": []
            },
            "duration": 1,
            "language": "axaml"
          },
          {
            "timestamp": "2025-10-21T18:48:44.737Z",
            "fileName": "c:\\Users\\ludov\\Documents\\Code\\C#\\SkinTrack\\SkinTrack\\Views\\CarsView.axaml",
            "fileType": ".axaml",
            "linesAdded": 0,
            "linesRemoved": 4,
            "projectName": "SkinTrack",
            "content": {
              "added": [],
              "removed": []
            },
            "duration": 1,
            "language": "axaml"
          },
          {
            "timestamp": "2025-10-21T18:48:45.997Z",
            "fileName": "c:\\Users\\ludov\\Documents\\Code\\C#\\SkinTrack\\SkinTrack\\Views\\CarsView.axaml",
            "fileType": ".axaml",
            "linesAdded": 0,
            "linesRemoved": 1,
            "projectName": "SkinTrack",
            "content": {
              "added": [],
              "removed": []
            },
            "duration": 1,
            "language": "axaml"
          },
          {
            "timestamp": "2025-10-21T18:48:52.113Z",
            "fileName": "c:\\Users\\ludov\\Documents\\Code\\C#\\SkinTrack\\SkinTrack\\Views\\CarsView.axaml",
            "fileType": ".axaml",
            "linesAdded": 4,
            "linesRemoved": 0,
            "projectName": "SkinTrack",
            "content": {
              "added": [],
              "removed": []
            },
            "duration": 1,
            "language": "axaml"
          },
          {
            "timestamp": "2025-10-21T18:48:58.772Z",
            "fileName": "c:\\Users\\ludov\\Documents\\Code\\C#\\SkinTrack\\SkinTrack\\Views\\CarsView.axaml",
            "fileType": ".axaml",
            "linesAdded": 0,
            "linesRemoved": 3,
            "projectName": "SkinTrack",
            "content": {
              "added": [],
              "removed": []
            },
            "duration": 1,
            "language": "axaml"
          },
          {
            "timestamp": "2025-10-21T18:49:19.034Z",
            "fileName": "c:\\Users\\ludov\\Documents\\Code\\C#\\SkinTrack\\SkinTrack\\Views\\CarsView.axaml",
            "fileType": ".axaml",
            "linesAdded": 0,
            "linesRemoved": 1,
            "projectName": "SkinTrack",
            "content": {
              "added": [],
              "removed": []
            },
            "duration": 1,
            "language": "axaml"
          },
          {
            "timestamp": "2025-10-21T18:49:20.589Z",
            "fileName": "c:\\Users\\ludov\\Documents\\Code\\C#\\SkinTrack\\SkinTrack\\Views\\CarsView.axaml",
            "fileType": ".axaml",
            "linesAdded": 2,
            "linesRemoved": 0,
            "projectName": "SkinTrack",
            "content": {
              "added": [],
              "removed": []
            },
            "duration": 1,
            "language": "axaml"
          },
          {
            "timestamp": "2025-10-21T18:49:28.398Z",
            "fileName": "c:\\Users\\ludov\\Documents\\Code\\C#\\SkinTrack\\SkinTrack\\Views\\CarsView.axaml",
            "fileType": ".axaml",
            "linesAdded": 1,
            "linesRemoved": 0,
            "projectName": "SkinTrack",
            "content": {
              "added": [],
              "removed": []
            },
            "duration": 1,
            "language": "axaml"
          },
          {
            "timestamp": "2025-10-21T18:49:33.823Z",
            "fileName": "c:\\Users\\ludov\\Documents\\Code\\C#\\SkinTrack\\SkinTrack\\Views\\CarsView.axaml",
            "fileType": ".axaml",
            "linesAdded": 1,
            "linesRemoved": 0,
            "projectName": "SkinTrack",
            "content": {
              "added": [],
              "removed": []
            },
            "duration": 1,
            "language": "axaml"
          },
          {
            "timestamp": "2025-10-21T18:49:37.194Z",
            "fileName": "c:\\Users\\ludov\\Documents\\Code\\C#\\SkinTrack\\SkinTrack\\Views\\CarsView.axaml",
            "fileType": ".axaml",
            "linesAdded": 1,
            "linesRemoved": 0,
            "projectName": "SkinTrack",
            "content": {
              "added": [],
              "removed": []
            },
            "duration": 1,
            "language": "axaml"
          },
          {
            "timestamp": "2025-10-21T18:49:41.997Z",
            "fileName": "c:\\Users\\ludov\\Documents\\Code\\C#\\SkinTrack\\SkinTrack\\Views\\CarsView.axaml",
            "fileType": ".axaml",
            "linesAdded": 1,
            "linesRemoved": 0,
            "projectName": "SkinTrack",
            "content": {
              "added": [],
              "removed": []
            },
            "duration": 1,
            "language": "axaml"
          },
          {
            "timestamp": "2025-10-21T18:49:52.352Z",
            "fileName": "c:\\Users\\ludov\\Documents\\Code\\C#\\SkinTrack\\SkinTrack\\Views\\CarsView.axaml",
            "fileType": ".axaml",
            "linesAdded": 0,
            "linesRemoved": 6,
            "projectName": "SkinTrack",
            "content": {
              "added": [],
              "removed": []
            },
            "duration": 1,
            "language": "axaml"
          },
          {
            "timestamp": "2025-10-21T18:50:06.557Z",
            "fileName": "c:\\Users\\ludov\\Documents\\Code\\C#\\SkinTrack\\SkinTrack\\Views\\CarsView.axaml",
            "fileType": ".axaml",
            "linesAdded": 1,
            "linesRemoved": 0,
            "projectName": "SkinTrack",
            "content": {
              "added": [],
              "removed": []
            },
            "duration": 1,
            "language": "axaml"
          },
          {
            "timestamp": "2025-10-21T18:50:57.273Z",
            "fileName": "c:\\Users\\ludov\\Documents\\Code\\C#\\SkinTrack\\SkinTrack\\Views\\CarsView.axaml",
            "fileType": ".axaml",
            "linesAdded": 0,
            "linesRemoved": 1,
            "projectName": "SkinTrack",
            "content": {
              "added": [],
              "removed": []
            },
            "duration": 1,
            "language": "axaml"
          },
          {
            "timestamp": "2025-10-21T18:50:59.068Z",
            "fileName": "c:\\Users\\ludov\\Documents\\Code\\C#\\SkinTrack\\SkinTrack\\Views\\CarsView.axaml",
            "fileType": ".axaml",
            "linesAdded": 1,
            "linesRemoved": 0,
            "projectName": "SkinTrack",
            "content": {
              "added": [],
              "removed": []
            },
            "duration": 1,
            "language": "axaml"
          },
          {
            "timestamp": "2025-10-21T18:51:00.229Z",
            "fileName": "c:\\Users\\ludov\\Documents\\Code\\C#\\SkinTrack\\SkinTrack\\Views\\CarsView.axaml",
            "fileType": ".axaml",
            "linesAdded": 4,
            "linesRemoved": 0,
            "projectName": "SkinTrack",
            "content": {
              "added": [],
              "removed": []
            },
            "duration": 1,
            "language": "axaml"
          },
          {
            "timestamp": "2025-10-21T18:51:16.596Z",
            "fileName": "c:\\Users\\ludov\\Documents\\Code\\C#\\SkinTrack\\SkinTrack\\Views\\CarsView.axaml",
            "fileType": ".axaml",
            "linesAdded": 0,
            "linesRemoved": 5,
            "projectName": "SkinTrack",
            "content": {
              "added": [],
              "removed": []
            },
            "duration": 1,
            "language": "axaml"
          }
        ],
        "c:\\Users\\ludov\\Documents\\Code\\C#\\SkinTrack\\SkinTrack\\Views\\HomeView.axaml": [
          {
            "timestamp": "2025-10-21T17:34:49.942Z",
            "fileName": "c:\\Users\\ludov\\Documents\\Code\\C#\\SkinTrack\\SkinTrack\\Views\\HomeView.axaml",
            "fileType": ".axaml",
            "linesAdded": 13,
            "linesRemoved": 0,
            "projectName": "SkinTrack",
            "content": {
              "added": [],
              "removed": []
            },
            "duration": 1,
            "language": "axaml"
          },
          {
            "timestamp": "2025-10-21T17:34:50.951Z",
            "fileName": "c:\\Users\\ludov\\Documents\\Code\\C#\\SkinTrack\\SkinTrack\\Views\\HomeView.axaml",
            "fileType": ".axaml",
            "linesAdded": 1,
            "linesRemoved": 0,
            "projectName": "SkinTrack",
            "content": {
              "added": [],
              "removed": []
            },
            "duration": 1,
            "language": "axaml"
          },
          {
            "timestamp": "2025-10-21T17:35:06.874Z",
            "fileName": "c:\\Users\\ludov\\Documents\\Code\\C#\\SkinTrack\\SkinTrack\\Views\\HomeView.axaml",
            "fileType": ".axaml",
            "linesAdded": 1,
            "linesRemoved": 0,
            "projectName": "SkinTrack",
            "content": {
              "added": [],
              "removed": []
            },
            "duration": 1,
            "language": "axaml"
          },
          {
            "timestamp": "2025-10-21T17:52:54.469Z",
            "fileName": "c:\\Users\\ludov\\Documents\\Code\\C#\\SkinTrack\\SkinTrack\\Views\\HomeView.axaml",
            "fileType": ".axaml",
            "linesAdded": 15,
            "linesRemoved": 0,
            "projectName": "SkinTrack",
            "content": {
              "added": [],
              "removed": []
            },
            "duration": 0,
            "language": "axaml"
          },
          {
            "timestamp": "2025-10-21T17:56:05.697Z",
            "fileName": "c:\\Users\\ludov\\Documents\\Code\\C#\\SkinTrack\\SkinTrack\\Views\\HomeView.axaml",
            "fileType": ".axaml",
            "linesAdded": 0,
            "linesRemoved": 2,
            "projectName": "SkinTrack",
            "content": {
              "added": [],
              "removed": []
            },
            "duration": 1,
            "language": "axaml"
          },
          {
            "timestamp": "2025-10-21T17:56:23.129Z",
            "fileName": "c:\\Users\\ludov\\Documents\\Code\\C#\\SkinTrack\\SkinTrack\\Views\\HomeView.axaml",
            "fileType": ".axaml",
            "linesAdded": 2,
            "linesRemoved": 0,
            "projectName": "SkinTrack",
            "content": {
              "added": [],
              "removed": []
            },
            "duration": 1,
            "language": "axaml"
          },
          {
            "timestamp": "2025-10-21T17:58:41.734Z",
            "fileName": "c:\\Users\\ludov\\Documents\\Code\\C#\\SkinTrack\\SkinTrack\\Views\\HomeView.axaml",
            "fileType": ".axaml",
            "linesAdded": 1,
            "linesRemoved": 0,
            "projectName": "SkinTrack",
            "content": {
              "added": [],
              "removed": []
            },
            "duration": 1,
            "language": "axaml"
          },
          {
            "timestamp": "2025-10-21T17:59:37.832Z",
            "fileName": "c:\\Users\\ludov\\Documents\\Code\\C#\\SkinTrack\\SkinTrack\\Views\\HomeView.axaml",
            "fileType": ".axaml",
            "linesAdded": 1,
            "linesRemoved": 0,
            "projectName": "SkinTrack",
            "content": {
              "added": [],
              "removed": []
            },
            "duration": 1,
            "language": "axaml"
          },
          {
            "timestamp": "2025-10-21T18:00:57.073Z",
            "fileName": "c:\\Users\\ludov\\Documents\\Code\\C#\\SkinTrack\\SkinTrack\\Views\\HomeView.axaml",
            "fileType": ".axaml",
            "linesAdded": 1,
            "linesRemoved": 0,
            "projectName": "SkinTrack",
            "content": {
              "added": [],
              "removed": []
            },
            "duration": 2,
            "language": "axaml"
          },
          {
            "timestamp": "2025-10-21T18:01:13.136Z",
            "fileName": "c:\\Users\\ludov\\Documents\\Code\\C#\\SkinTrack\\SkinTrack\\Views\\HomeView.axaml",
            "fileType": ".axaml",
            "linesAdded": 0,
            "linesRemoved": 1,
            "projectName": "SkinTrack",
            "content": {
              "added": [],
              "removed": []
            },
            "duration": 1,
            "language": "axaml"
          },
          {
            "timestamp": "2025-10-21T18:01:15.446Z",
            "fileName": "c:\\Users\\ludov\\Documents\\Code\\C#\\SkinTrack\\SkinTrack\\Views\\HomeView.axaml",
            "fileType": ".axaml",
            "linesAdded": 2,
            "linesRemoved": 0,
            "projectName": "SkinTrack",
            "content": {
              "added": [],
              "removed": []
            },
            "duration": 1,
            "language": "axaml"
          },
          {
            "timestamp": "2025-10-21T18:01:18.019Z",
            "fileName": "c:\\Users\\ludov\\Documents\\Code\\C#\\SkinTrack\\SkinTrack\\Views\\HomeView.axaml",
            "fileType": ".axaml",
            "linesAdded": 0,
            "linesRemoved": 2,
            "projectName": "SkinTrack",
            "content": {
              "added": [],
              "removed": []
            },
            "duration": 1,
            "language": "axaml"
          },
          {
            "timestamp": "2025-10-21T18:01:23.737Z",
            "fileName": "c:\\Users\\ludov\\Documents\\Code\\C#\\SkinTrack\\SkinTrack\\Views\\HomeView.axaml",
            "fileType": ".axaml",
            "linesAdded": 2,
            "linesRemoved": 0,
            "projectName": "SkinTrack",
            "content": {
              "added": [],
              "removed": []
            },
            "duration": 1,
            "language": "axaml"
          },
          {
            "timestamp": "2025-10-21T18:01:51.757Z",
            "fileName": "c:\\Users\\ludov\\Documents\\Code\\C#\\SkinTrack\\SkinTrack\\Views\\HomeView.axaml",
            "fileType": ".axaml",
            "linesAdded": 2,
            "linesRemoved": 0,
            "projectName": "SkinTrack",
            "content": {
              "added": [],
              "removed": []
            },
            "duration": 1,
            "language": "axaml"
          },
          {
            "timestamp": "2025-10-21T18:01:59.339Z",
            "fileName": "c:\\Users\\ludov\\Documents\\Code\\C#\\SkinTrack\\SkinTrack\\Views\\HomeView.axaml",
            "fileType": ".axaml",
            "linesAdded": 1,
            "linesRemoved": 0,
            "projectName": "SkinTrack",
            "content": {
              "added": [],
              "removed": []
            },
            "duration": 1,
            "language": "axaml"
          },
          {
            "timestamp": "2025-10-21T18:02:06.484Z",
            "fileName": "c:\\Users\\ludov\\Documents\\Code\\C#\\SkinTrack\\SkinTrack\\Views\\HomeView.axaml",
            "fileType": ".axaml",
            "linesAdded": 0,
            "linesRemoved": 1,
            "projectName": "SkinTrack",
            "content": {
              "added": [],
              "removed": []
            },
            "duration": 1,
            "language": "axaml"
          },
          {
            "timestamp": "2025-10-21T18:02:10.867Z",
            "fileName": "c:\\Users\\ludov\\Documents\\Code\\C#\\SkinTrack\\SkinTrack\\Views\\HomeView.axaml",
            "fileType": ".axaml",
            "linesAdded": 1,
            "linesRemoved": 0,
            "projectName": "SkinTrack",
            "content": {
              "added": [],
              "removed": []
            },
            "duration": 1,
            "language": "axaml"
          },
          {
            "timestamp": "2025-10-21T18:02:18.307Z",
            "fileName": "c:\\Users\\ludov\\Documents\\Code\\C#\\SkinTrack\\SkinTrack\\Views\\HomeView.axaml",
            "fileType": ".axaml",
            "linesAdded": 0,
            "linesRemoved": 1,
            "projectName": "SkinTrack",
            "content": {
              "added": [],
              "removed": []
            },
            "duration": 1,
            "language": "axaml"
          },
          {
            "timestamp": "2025-10-21T18:02:21.047Z",
            "fileName": "c:\\Users\\ludov\\Documents\\Code\\C#\\SkinTrack\\SkinTrack\\Views\\HomeView.axaml",
            "fileType": ".axaml",
            "linesAdded": 1,
            "linesRemoved": 0,
            "projectName": "SkinTrack",
            "content": {
              "added": [],
              "removed": []
            },
            "duration": 1,
            "language": "axaml"
          },
          {
            "timestamp": "2025-10-21T18:02:33.700Z",
            "fileName": "c:\\Users\\ludov\\Documents\\Code\\C#\\SkinTrack\\SkinTrack\\Views\\HomeView.axaml",
            "fileType": ".axaml",
            "linesAdded": 1,
            "linesRemoved": 0,
            "projectName": "SkinTrack",
            "content": {
              "added": [],
              "removed": []
            },
            "duration": 1,
            "language": "axaml"
          },
          {
            "timestamp": "2025-10-21T18:02:36.100Z",
            "fileName": "c:\\Users\\ludov\\Documents\\Code\\C#\\SkinTrack\\SkinTrack\\Views\\HomeView.axaml",
            "fileType": ".axaml",
            "linesAdded": 11,
            "linesRemoved": 0,
            "projectName": "SkinTrack",
            "content": {
              "added": [],
              "removed": []
            },
            "duration": 1,
            "language": "axaml"
          },
          {
            "timestamp": "2025-10-21T18:04:18.336Z",
            "fileName": "c:\\Users\\ludov\\Documents\\Code\\C#\\SkinTrack\\SkinTrack\\Views\\HomeView.axaml",
            "fileType": ".axaml",
            "linesAdded": 0,
            "linesRemoved": 2,
            "projectName": "SkinTrack",
            "content": {
              "added": [],
              "removed": []
            },
            "duration": 2,
            "language": "axaml"
          },
          {
            "timestamp": "2025-10-21T18:04:45.714Z",
            "fileName": "c:\\Users\\ludov\\Documents\\Code\\C#\\SkinTrack\\SkinTrack\\Views\\HomeView.axaml",
            "fileType": ".axaml",
            "linesAdded": 0,
            "linesRemoved": 1,
            "projectName": "SkinTrack",
            "content": {
              "added": [],
              "removed": []
            },
            "duration": 1,
            "language": "axaml"
          },
          {
            "timestamp": "2025-10-21T18:05:00.345Z",
            "fileName": "c:\\Users\\ludov\\Documents\\Code\\C#\\SkinTrack\\SkinTrack\\Views\\HomeView.axaml",
            "fileType": ".axaml",
            "linesAdded": 0,
            "linesRemoved": 1,
            "projectName": "SkinTrack",
            "content": {
              "added": [],
              "removed": []
            },
            "duration": 1,
            "language": "axaml"
          }
        ],
        "c:\\Users\\ludov\\Documents\\Code\\C#\\SkinTrack\\SkinTrack\\Views\\HomeView.axaml.cs": [
          {
            "timestamp": "2025-10-21T17:36:40.782Z",
            "fileName": "c:\\Users\\ludov\\Documents\\Code\\C#\\SkinTrack\\SkinTrack\\Views\\HomeView.axaml.cs",
            "fileType": ".cs",
            "linesAdded": 19,
            "linesRemoved": 0,
            "projectName": "SkinTrack",
            "content": {
              "added": [],
              "removed": []
            },
            "duration": 2,
            "language": "cs"
          },
          {
            "timestamp": "2025-10-21T17:55:34.542Z",
            "fileName": "c:\\Users\\ludov\\Documents\\Code\\C#\\SkinTrack\\SkinTrack\\Views\\HomeView.axaml.cs",
            "fileType": ".cs",
            "linesAdded": 29,
            "linesRemoved": 0,
            "projectName": "SkinTrack",
            "content": {
              "added": [],
              "removed": []
            },
            "duration": 3,
            "language": "cs"
          },
          {
            "timestamp": "2025-10-21T17:55:35.551Z",
            "fileName": "c:\\Users\\ludov\\Documents\\Code\\C#\\SkinTrack\\SkinTrack\\Views\\HomeView.axaml.cs",
            "fileType": ".cs",
            "linesAdded": 0,
            "linesRemoved": 14,
            "projectName": "SkinTrack",
            "content": {
              "added": [],
              "removed": []
            },
            "duration": 1,
            "language": "cs"
          },
          {
            "timestamp": "2025-10-21T17:55:37.322Z",
            "fileName": "c:\\Users\\ludov\\Documents\\Code\\C#\\SkinTrack\\SkinTrack\\Views\\HomeView.axaml.cs",
            "fileType": ".cs",
            "linesAdded": 0,
            "linesRemoved": 1,
            "projectName": "SkinTrack",
            "content": {
              "added": [],
              "removed": []
            },
            "duration": 1,
            "language": "cs"
          }
        ],
        "c:\\Users\\ludov\\Documents\\Code\\C#\\SkinTrack\\.vscode\\settings.json": [
          {
            "timestamp": "2025-10-21T17:40:54.609Z",
            "fileName": "c:\\Users\\ludov\\Documents\\Code\\C#\\SkinTrack\\.vscode\\settings.json",
            "fileType": ".json",
            "linesAdded": 10,
            "linesRemoved": 0,
            "projectName": "SkinTrack",
            "content": {
              "added": [],
              "removed": []
            },
            "duration": 0,
            "language": "json"
          }
        ],
        "c:\\Users\\ludov\\Documents\\Code\\C#\\SkinTrack\\SkinTrack\\SkinTrack.csproj": [
          {
            "timestamp": "2025-10-21T17:41:26.359Z",
            "fileName": "c:\\Users\\ludov\\Documents\\Code\\C#\\SkinTrack\\SkinTrack\\SkinTrack.csproj",
            "fileType": ".csproj",
            "linesAdded": 33,
            "linesRemoved": 0,
            "projectName": "SkinTrack",
            "content": {
              "added": [],
              "removed": []
            },
            "duration": 1,
            "language": "csproj"
          }
        ],
        "c:\\Users\\ludov\\Documents\\Code\\C#\\SkinTrack\\SkinTrack\\Data\\AppDbContext.cs": [
          {
            "timestamp": "2025-10-21T17:42:15.819Z",
            "fileName": "c:\\Users\\ludov\\Documents\\Code\\C#\\SkinTrack\\SkinTrack\\Data\\AppDbContext.cs",
            "fileType": ".cs",
            "linesAdded": 26,
            "linesRemoved": 0,
            "projectName": "SkinTrack",
            "content": {
              "added": [],
              "removed": []
            },
            "duration": 1,
            "language": "cs"
          }
        ],
        "c:\\Users\\ludov\\Documents\\Code\\C#\\SkinTrack\\SkinTrack\\Program.cs": [
          {
            "timestamp": "2025-10-21T17:43:22.495Z",
            "fileName": "c:\\Users\\ludov\\Documents\\Code\\C#\\SkinTrack\\SkinTrack\\Program.cs",
            "fileType": ".cs",
            "linesAdded": 36,
            "linesRemoved": 0,
            "projectName": "SkinTrack",
            "content": {
              "added": [],
              "removed": []
            },
            "duration": 2,
            "language": "cs"
          }
        ],
        "c:\\Users\\ludov\\Documents\\Code\\C#\\SkinTrack\\SkinTrack\\Views\\MainWindow.axaml.cs": [
          {
            "timestamp": "2025-10-21T17:44:16.063Z",
            "fileName": "c:\\Users\\ludov\\Documents\\Code\\C#\\SkinTrack\\SkinTrack\\Views\\MainWindow.axaml.cs",
            "fileType": ".cs",
            "linesAdded": 13,
            "linesRemoved": 0,
            "projectName": "SkinTrack",
            "content": {
              "added": [],
              "removed": []
            },
            "duration": 1,
            "language": "cs"
          },
          {
            "timestamp": "2025-10-21T17:44:17.076Z",
            "fileName": "c:\\Users\\ludov\\Documents\\Code\\C#\\SkinTrack\\SkinTrack\\Views\\MainWindow.axaml.cs",
            "fileType": ".cs",
            "linesAdded": 0,
            "linesRemoved": 1,
            "projectName": "SkinTrack",
            "content": {
              "added": [],
              "removed": []
            },
            "duration": 1,
            "language": "cs"
          },
          {
            "timestamp": "2025-10-21T17:44:54.210Z",
            "fileName": "c:\\Users\\ludov\\Documents\\Code\\C#\\SkinTrack\\SkinTrack\\Views\\MainWindow.axaml.cs",
            "fileType": ".cs",
            "linesAdded": 0,
            "linesRemoved": 1,
            "projectName": "SkinTrack",
            "content": {
              "added": [],
              "removed": []
            },
            "duration": 1,
            "language": "cs"
          },
          {
            "timestamp": "2025-10-21T17:55:39.751Z",
            "fileName": "c:\\Users\\ludov\\Documents\\Code\\C#\\SkinTrack\\SkinTrack\\Views\\MainWindow.axaml.cs",
            "fileType": ".cs",
            "linesAdded": 11,
            "linesRemoved": 0,
            "projectName": "SkinTrack",
            "content": {
              "added": [],
              "removed": []
            },
            "duration": 1,
            "language": "cs"
          },
          {
            "timestamp": "2025-10-21T17:55:41.776Z",
            "fileName": "c:\\Users\\ludov\\Documents\\Code\\C#\\SkinTrack\\SkinTrack\\Views\\MainWindow.axaml.cs",
            "fileType": ".cs",
            "linesAdded": 16,
            "linesRemoved": 0,
            "projectName": "SkinTrack",
            "content": {
              "added": [],
              "removed": []
            },
            "duration": 1,
            "language": "cs"
          },
          {
            "timestamp": "2025-10-21T17:55:45.228Z",
            "fileName": "c:\\Users\\ludov\\Documents\\Code\\C#\\SkinTrack\\SkinTrack\\Views\\MainWindow.axaml.cs",
            "fileType": ".cs",
            "linesAdded": 0,
            "linesRemoved": 1,
            "projectName": "SkinTrack",
            "content": {
              "added": [],
              "removed": []
            },
            "duration": 1,
            "language": "cs"
          },
          {
            "timestamp": "2025-10-21T17:55:49.587Z",
            "fileName": "c:\\Users\\ludov\\Documents\\Code\\C#\\SkinTrack\\SkinTrack\\Views\\MainWindow.axaml.cs",
            "fileType": ".cs",
            "linesAdded": 1,
            "linesRemoved": 0,
            "projectName": "SkinTrack",
            "content": {
              "added": [],
              "removed": []
            },
            "duration": 1,
            "language": "cs"
          }
        ],
        "c:\\Users\\ludov\\Documents\\Code\\C#\\SkinTrack\\SkinTrack\\Views\\MainWindow.axaml": [
          {
            "timestamp": "2025-10-21T17:45:12.096Z",
            "fileName": "c:\\Users\\ludov\\Documents\\Code\\C#\\SkinTrack\\SkinTrack\\Views\\MainWindow.axaml",
            "fileType": ".axaml",
            "linesAdded": 36,
            "linesRemoved": 0,
            "projectName": "SkinTrack",
            "content": {
              "added": [],
              "removed": []
            },
            "duration": 1,
            "language": "axaml"
          },
          {
            "timestamp": "2025-10-21T17:56:32.852Z",
            "fileName": "c:\\Users\\ludov\\Documents\\Code\\C#\\SkinTrack\\SkinTrack\\Views\\MainWindow.axaml",
            "fileType": ".axaml",
            "linesAdded": 36,
            "linesRemoved": 0,
            "projectName": "SkinTrack",
            "content": {
              "added": [],
              "removed": []
            },
            "duration": 1,
            "language": "axaml"
          },
          {
            "timestamp": "2025-10-21T17:56:33.862Z",
            "fileName": "c:\\Users\\ludov\\Documents\\Code\\C#\\SkinTrack\\SkinTrack\\Views\\MainWindow.axaml",
            "fileType": ".axaml",
            "linesAdded": 1,
            "linesRemoved": 0,
            "projectName": "SkinTrack",
            "content": {
              "added": [],
              "removed": []
            },
            "duration": 1,
            "language": "axaml"
          },
          {
            "timestamp": "2025-10-21T17:56:53.322Z",
            "fileName": "c:\\Users\\ludov\\Documents\\Code\\C#\\SkinTrack\\SkinTrack\\Views\\MainWindow.axaml",
            "fileType": ".axaml",
            "linesAdded": 10,
            "linesRemoved": 0,
            "projectName": "SkinTrack",
            "content": {
              "added": [],
              "removed": []
            },
            "duration": 1,
            "language": "axaml"
          },
          {
            "timestamp": "2025-10-21T17:57:09.420Z",
            "fileName": "c:\\Users\\ludov\\Documents\\Code\\C#\\SkinTrack\\SkinTrack\\Views\\MainWindow.axaml",
            "fileType": ".axaml",
            "linesAdded": 0,
            "linesRemoved": 11,
            "projectName": "SkinTrack",
            "content": {
              "added": [],
              "removed": []
            },
            "duration": 1,
            "language": "axaml"
          },
          {
            "timestamp": "2025-10-21T17:57:11.712Z",
            "fileName": "c:\\Users\\ludov\\Documents\\Code\\C#\\SkinTrack\\SkinTrack\\Views\\MainWindow.axaml",
            "fileType": ".axaml",
            "linesAdded": 1,
            "linesRemoved": 0,
            "projectName": "SkinTrack",
            "content": {
              "added": [],
              "removed": []
            },
            "duration": 1,
            "language": "axaml"
          },
          {
            "timestamp": "2025-10-21T17:57:17.370Z",
            "fileName": "c:\\Users\\ludov\\Documents\\Code\\C#\\SkinTrack\\SkinTrack\\Views\\MainWindow.axaml",
            "fileType": ".axaml",
            "linesAdded": 10,
            "linesRemoved": 0,
            "projectName": "SkinTrack",
            "content": {
              "added": [],
              "removed": []
            },
            "duration": 1,
            "language": "axaml"
          },
          {
            "timestamp": "2025-10-21T17:57:20.486Z",
            "fileName": "c:\\Users\\ludov\\Documents\\Code\\C#\\SkinTrack\\SkinTrack\\Views\\MainWindow.axaml",
            "fileType": ".axaml",
            "linesAdded": 0,
            "linesRemoved": 10,
            "projectName": "SkinTrack",
            "content": {
              "added": [],
              "removed": []
            },
            "duration": 1,
            "language": "axaml"
          },
          {
            "timestamp": "2025-10-21T17:57:22.430Z",
            "fileName": "c:\\Users\\ludov\\Documents\\Code\\C#\\SkinTrack\\SkinTrack\\Views\\MainWindow.axaml",
            "fileType": ".axaml",
            "linesAdded": 10,
            "linesRemoved": 0,
            "projectName": "SkinTrack",
            "content": {
              "added": [],
              "removed": []
            },
            "duration": 1,
            "language": "axaml"
          },
          {
            "timestamp": "2025-10-21T17:58:02.141Z",
            "fileName": "c:\\Users\\ludov\\Documents\\Code\\C#\\SkinTrack\\SkinTrack\\Views\\MainWindow.axaml",
            "fileType": ".axaml",
            "linesAdded": 0,
            "linesRemoved": 11,
            "projectName": "SkinTrack",
            "content": {
              "added": [],
              "removed": []
            },
            "duration": 1,
            "language": "axaml"
          },
          {
            "timestamp": "2025-10-21T17:58:07.056Z",
            "fileName": "c:\\Users\\ludov\\Documents\\Code\\C#\\SkinTrack\\SkinTrack\\Views\\MainWindow.axaml",
            "fileType": ".axaml",
            "linesAdded": 5,
            "linesRemoved": 0,
            "projectName": "SkinTrack",
            "content": {
              "added": [],
              "removed": []
            },
            "duration": 1,
            "language": "axaml"
          },
          {
            "timestamp": "2025-10-21T17:58:20.325Z",
            "fileName": "c:\\Users\\ludov\\Documents\\Code\\C#\\SkinTrack\\SkinTrack\\Views\\MainWindow.axaml",
            "fileType": ".axaml",
            "linesAdded": 0,
            "linesRemoved": 4,
            "projectName": "SkinTrack",
            "content": {
              "added": [],
              "removed": []
            },
            "duration": 1,
            "language": "axaml"
          },
          {
            "timestamp": "2025-10-21T17:58:22.806Z",
            "fileName": "c:\\Users\\ludov\\Documents\\Code\\C#\\SkinTrack\\SkinTrack\\Views\\MainWindow.axaml",
            "fileType": ".axaml",
            "linesAdded": 0,
            "linesRemoved": 1,
            "projectName": "SkinTrack",
            "content": {
              "added": [],
              "removed": []
            },
            "duration": 1,
            "language": "axaml"
          },
          {
            "timestamp": "2025-10-21T18:04:26.719Z",
            "fileName": "c:\\Users\\ludov\\Documents\\Code\\C#\\SkinTrack\\SkinTrack\\Views\\MainWindow.axaml",
            "fileType": ".axaml",
            "linesAdded": 3,
            "linesRemoved": 0,
            "projectName": "SkinTrack",
            "content": {
              "added": [],
              "removed": []
            },
            "duration": 1,
            "language": "axaml"
          },
          {
            "timestamp": "2025-10-21T18:04:27.936Z",
            "fileName": "c:\\Users\\ludov\\Documents\\Code\\C#\\SkinTrack\\SkinTrack\\Views\\MainWindow.axaml",
            "fileType": ".axaml",
            "linesAdded": 8,
            "linesRemoved": 0,
            "projectName": "SkinTrack",
            "content": {
              "added": [],
              "removed": []
            },
            "duration": 1,
            "language": "axaml"
          },
          {
            "timestamp": "2025-10-21T18:04:34.022Z",
            "fileName": "c:\\Users\\ludov\\Documents\\Code\\C#\\SkinTrack\\SkinTrack\\Views\\MainWindow.axaml",
            "fileType": ".axaml",
            "linesAdded": 0,
            "linesRemoved": 1,
            "projectName": "SkinTrack",
            "content": {
              "added": [],
              "removed": []
            },
            "duration": 1,
            "language": "axaml"
          },
          {
            "timestamp": "2025-10-21T18:11:22.566Z",
            "fileName": "c:\\Users\\ludov\\Documents\\Code\\C#\\SkinTrack\\SkinTrack\\Views\\MainWindow.axaml",
            "fileType": ".axaml",
            "linesAdded": 46,
            "linesRemoved": 0,
            "projectName": "SkinTrack",
            "content": {
              "added": [],
              "removed": []
            },
            "duration": 1,
            "language": "axaml"
          },
          {
            "timestamp": "2025-10-21T18:11:23.592Z",
            "fileName": "c:\\Users\\ludov\\Documents\\Code\\C#\\SkinTrack\\SkinTrack\\Views\\MainWindow.axaml",
            "fileType": ".axaml",
            "linesAdded": 1,
            "linesRemoved": 0,
            "projectName": "SkinTrack",
            "content": {
              "added": [],
              "removed": []
            },
            "duration": 1,
            "language": "axaml"
          }
        ],
        "c:\\Users\\ludov\\Documents\\Code\\C#\\SkinTrack\\SkinTrack\\App.axaml": [
          {
            "timestamp": "2025-10-21T18:11:19.948Z",
            "fileName": "c:\\Users\\ludov\\Documents\\Code\\C#\\SkinTrack\\SkinTrack\\App.axaml",
            "fileType": ".axaml",
            "linesAdded": 15,
            "linesRemoved": 0,
            "projectName": "SkinTrack",
            "content": {
              "added": [],
              "removed": []
            },
            "duration": 0,
            "language": "axaml"
          },
          {
            "timestamp": "2025-10-21T18:11:20.961Z",
            "fileName": "c:\\Users\\ludov\\Documents\\Code\\C#\\SkinTrack\\SkinTrack\\App.axaml",
            "fileType": ".axaml",
            "linesAdded": 2,
            "linesRemoved": 0,
            "projectName": "SkinTrack",
            "content": {
              "added": [],
              "removed": []
            },
            "duration": 1,
            "language": "axaml"
          }
        ]
      },
      "languageStats": {
        "axaml": 1
      },
      "changeFrequency": {
        "17": 1
      },
      "topFiles": [
        "c:\\Users\\ludov\\Documents\\Code\\C#\\SkinTrack\\SkinTrack\\Views\\CarsView.axaml"
      ],
      "averageChangeSize": 7.5
    }
  },
  "totalActiveTime": 1,
  "totalProjects": 1,
  "totalFiles": 1,
  "mostActiveHours": [
    17
  ],
  "mostUsedLanguages": [
    "axaml"
  ]
}