{
  "date": "2025-05-03",
  "projects": {
    "date": {
      "totalLinesAdded": 1247,
      "totalLinesRemoved": 102,
      "totalActiveTime": 226,
      "files": {
        "c:\\Users\\ludov\\Documents\\Code\\C++\\Utilities\\date\\include\\day.hpp": [
          {
            "timestamp": "2025-05-02T21:57:25.573Z",
            "fileName": "c:\\Users\\ludov\\Documents\\Code\\C++\\Utilities\\date\\include\\day.hpp",
            "fileType": ".hpp",
            "linesAdded": 60,
            "linesRemoved": 0,
            "projectName": "date",
            "content": {
              "added": [],
              "removed": []
            },
            "duration": 2,
            "language": "hpp"
          },
          {
            "timestamp": "2025-05-02T21:57:26.697Z",
            "fileName": "c:\\Users\\ludov\\Documents\\Code\\C++\\Utilities\\date\\include\\day.hpp",
            "fileType": ".hpp",
            "linesAdded": 2,
            "linesRemoved": 0,
            "projectName": "date",
            "content": {
              "added": [],
              "removed": []
            },
            "duration": 1,
            "language": "hpp"
          },
          {
            "timestamp": "2025-05-03T14:24:20.738Z",
            "fileName": "c:\\Users\\ludov\\Documents\\Code\\C++\\Utilities\\date\\include\\day.hpp",
            "fileType": ".hpp",
            "linesAdded": 62,
            "linesRemoved": 0,
            "projectName": "date",
            "content": {
              "added": [],
              "removed": []
            },
            "duration": 1,
            "language": "hpp"
          },
          {
            "timestamp": "2025-05-03T14:24:21.786Z",
            "fileName": "c:\\Users\\ludov\\Documents\\Code\\C++\\Utilities\\date\\include\\day.hpp",
            "fileType": ".hpp",
            "linesAdded": 24,
            "linesRemoved": 0,
            "projectName": "date",
            "content": {
              "added": [],
              "removed": []
            },
            "duration": 1,
            "language": "hpp"
          },
          {
            "timestamp": "2025-05-03T14:24:23.357Z",
            "fileName": "c:\\Users\\ludov\\Documents\\Code\\C++\\Utilities\\date\\include\\day.hpp",
            "fileType": ".hpp",
            "linesAdded": 1,
            "linesRemoved": 0,
            "projectName": "date",
            "content": {
              "added": [],
              "removed": []
            },
            "duration": 1,
            "language": "hpp"
          }
        ],
        "c:\\Users\\ludov\\Documents\\Code\\C++\\Utilities\\date\\include\\month.hpp": [
          {
            "timestamp": "2025-05-02T21:57:43.897Z",
            "fileName": "c:\\Users\\ludov\\Documents\\Code\\C++\\Utilities\\date\\include\\month.hpp",
            "fileType": ".hpp",
            "linesAdded": 80,
            "linesRemoved": 0,
            "projectName": "date",
            "content": {
              "added": [],
              "removed": []
            },
            "duration": 1,
            "language": "hpp"
          },
          {
            "timestamp": "2025-05-02T21:57:45.045Z",
            "fileName": "c:\\Users\\ludov\\Documents\\Code\\C++\\Utilities\\date\\include\\month.hpp",
            "fileType": ".hpp",
            "linesAdded": 2,
            "linesRemoved": 0,
            "projectName": "date",
            "content": {
              "added": [],
              "removed": []
            },
            "duration": 1,
            "language": "hpp"
          },
          {
            "timestamp": "2025-05-03T14:24:39.875Z",
            "fileName": "c:\\Users\\ludov\\Documents\\Code\\C++\\Utilities\\date\\include\\month.hpp",
            "fileType": ".hpp",
            "linesAdded": 82,
            "linesRemoved": 0,
            "projectName": "date",
            "content": {
              "added": [],
              "removed": []
            },
            "duration": 1,
            "language": "hpp"
          },
          {
            "timestamp": "2025-05-03T14:24:41.591Z",
            "fileName": "c:\\Users\\ludov\\Documents\\Code\\C++\\Utilities\\date\\include\\month.hpp",
            "fileType": ".hpp",
            "linesAdded": 25,
            "linesRemoved": 0,
            "projectName": "date",
            "content": {
              "added": [],
              "removed": []
            },
            "duration": 1,
            "language": "hpp"
          }
        ],
        "c:\\Users\\ludov\\Documents\\Code\\C++\\Utilities\\date\\source\\main.cpp": [
          {
            "timestamp": "2025-05-02T21:58:15.545Z",
            "fileName": "c:\\Users\\ludov\\Documents\\Code\\C++\\Utilities\\date\\source\\main.cpp",
            "fileType": ".cpp",
            "linesAdded": 0,
            "linesRemoved": 1,
            "projectName": "date",
            "content": {
              "added": [],
              "removed": []
            },
            "duration": 1,
            "language": "cpp"
          },
          {
            "timestamp": "2025-05-02T21:58:38.460Z",
            "fileName": "c:\\Users\\ludov\\Documents\\Code\\C++\\Utilities\\date\\source\\main.cpp",
            "fileType": ".cpp",
            "linesAdded": 1,
            "linesRemoved": 0,
            "projectName": "date",
            "content": {
              "added": [],
              "removed": []
            },
            "duration": 1,
            "language": "cpp"
          },
          {
            "timestamp": "2025-05-02T22:15:29.442Z",
            "fileName": "c:\\Users\\ludov\\Documents\\Code\\C++\\Utilities\\date\\source\\main.cpp",
            "fileType": ".cpp",
            "linesAdded": 1,
            "linesRemoved": 0,
            "projectName": "date",
            "content": {
              "added": [],
              "removed": []
            },
            "duration": 1,
            "language": "cpp"
          },
          {
            "timestamp": "2025-05-02T22:15:34.794Z",
            "fileName": "c:\\Users\\ludov\\Documents\\Code\\C++\\Utilities\\date\\source\\main.cpp",
            "fileType": ".cpp",
            "linesAdded": 1,
            "linesRemoved": 0,
            "projectName": "date",
            "content": {
              "added": [],
              "removed": []
            },
            "duration": 1,
            "language": "cpp"
          },
          {
            "timestamp": "2025-05-02T22:15:45.171Z",
            "fileName": "c:\\Users\\ludov\\Documents\\Code\\C++\\Utilities\\date\\source\\main.cpp",
            "fileType": ".cpp",
            "linesAdded": 2,
            "linesRemoved": 0,
            "projectName": "date",
            "content": {
              "added": [],
              "removed": []
            },
            "duration": 1,
            "language": "cpp"
          },
          {
            "timestamp": "2025-05-03T13:41:17.723Z",
            "fileName": "c:\\Users\\ludov\\Documents\\Code\\C++\\Utilities\\date\\source\\main.cpp",
            "fileType": ".cpp",
            "linesAdded": 123,
            "linesRemoved": 0,
            "projectName": "date",
            "content": {
              "added": [],
              "removed": []
            },
            "duration": 0,
            "language": "cpp"
          },
          {
            "timestamp": "2025-05-03T13:41:18.729Z",
            "fileName": "c:\\Users\\ludov\\Documents\\Code\\C++\\Utilities\\date\\source\\main.cpp",
            "fileType": ".cpp",
            "linesAdded": 1,
            "linesRemoved": 0,
            "projectName": "date",
            "content": {
              "added": [],
              "removed": []
            },
            "duration": 1,
            "language": "cpp"
          },
          {
            "timestamp": "2025-05-03T13:41:27.094Z",
            "fileName": "c:\\Users\\ludov\\Documents\\Code\\C++\\Utilities\\date\\source\\main.cpp",
            "fileType": ".cpp",
            "linesAdded": 1,
            "linesRemoved": 0,
            "projectName": "date",
            "content": {
              "added": [],
              "removed": []
            },
            "duration": 1,
            "language": "cpp"
          },
          {
            "timestamp": "2025-05-03T13:48:16.200Z",
            "fileName": "c:\\Users\\ludov\\Documents\\Code\\C++\\Utilities\\date\\source\\main.cpp",
            "fileType": ".cpp",
            "linesAdded": 1,
            "linesRemoved": 0,
            "projectName": "date",
            "content": {
              "added": [],
              "removed": []
            },
            "duration": 1,
            "language": "cpp"
          },
          {
            "timestamp": "2025-05-03T13:48:35.488Z",
            "fileName": "c:\\Users\\ludov\\Documents\\Code\\C++\\Utilities\\date\\source\\main.cpp",
            "fileType": ".cpp",
            "linesAdded": 0,
            "linesRemoved": 1,
            "projectName": "date",
            "content": {
              "added": [],
              "removed": []
            },
            "duration": 1,
            "language": "cpp"
          },
          {
            "timestamp": "2025-05-03T13:49:47.065Z",
            "fileName": "c:\\Users\\ludov\\Documents\\Code\\C++\\Utilities\\date\\source\\main.cpp",
            "fileType": ".cpp",
            "linesAdded": 1,
            "linesRemoved": 0,
            "projectName": "date",
            "content": {
              "added": [],
              "removed": []
            },
            "duration": 1,
            "language": "cpp"
          },
          {
            "timestamp": "2025-05-03T13:52:38.242Z",
            "fileName": "c:\\Users\\ludov\\Documents\\Code\\C++\\Utilities\\date\\source\\main.cpp",
            "fileType": ".cpp",
            "linesAdded": 1,
            "linesRemoved": 0,
            "projectName": "date",
            "content": {
              "added": [],
              "removed": []
            },
            "duration": 1,
            "language": "cpp"
          },
          {
            "timestamp": "2025-05-03T13:53:03.240Z",
            "fileName": "c:\\Users\\ludov\\Documents\\Code\\C++\\Utilities\\date\\source\\main.cpp",
            "fileType": ".cpp",
            "linesAdded": 1,
            "linesRemoved": 0,
            "projectName": "date",
            "content": {
              "added": [],
              "removed": []
            },
            "duration": 1,
            "language": "cpp"
          },
          {
            "timestamp": "2025-05-03T13:53:10.153Z",
            "fileName": "c:\\Users\\ludov\\Documents\\Code\\C++\\Utilities\\date\\source\\main.cpp",
            "fileType": ".cpp",
            "linesAdded": 1,
            "linesRemoved": 0,
            "projectName": "date",
            "content": {
              "added": [],
              "removed": []
            },
            "duration": 1,
            "language": "cpp"
          },
          {
            "timestamp": "2025-05-03T13:55:31.945Z",
            "fileName": "c:\\Users\\ludov\\Documents\\Code\\C++\\Utilities\\date\\source\\main.cpp",
            "fileType": ".cpp",
            "linesAdded": 1,
            "linesRemoved": 0,
            "projectName": "date",
            "content": {
              "added": [],
              "removed": []
            },
            "duration": 1,
            "language": "cpp"
          },
          {
            "timestamp": "2025-05-03T14:01:20.542Z",
            "fileName": "c:\\Users\\ludov\\Documents\\Code\\C++\\Utilities\\date\\source\\main.cpp",
            "fileType": ".cpp",
            "linesAdded": 2,
            "linesRemoved": 0,
            "projectName": "date",
            "content": {
              "added": [],
              "removed": []
            },
            "duration": 1,
            "language": "cpp"
          },
          {
            "timestamp": "2025-05-03T14:13:57.024Z",
            "fileName": "c:\\Users\\ludov\\Documents\\Code\\C++\\Utilities\\date\\source\\main.cpp",
            "fileType": ".cpp",
            "linesAdded": 0,
            "linesRemoved": 1,
            "projectName": "date",
            "content": {
              "added": [],
              "removed": []
            },
            "duration": 2,
            "language": "cpp"
          },
          {
            "timestamp": "2025-05-03T14:15:31.115Z",
            "fileName": "c:\\Users\\ludov\\Documents\\Code\\C++\\Utilities\\date\\source\\main.cpp",
            "fileType": ".cpp",
            "linesAdded": 0,
            "linesRemoved": 1,
            "projectName": "date",
            "content": {
              "added": [],
              "removed": []
            },
            "duration": 1,
            "language": "cpp"
          },
          {
            "timestamp": "2025-05-03T14:16:16.166Z",
            "fileName": "c:\\Users\\ludov\\Documents\\Code\\C++\\Utilities\\date\\source\\main.cpp",
            "fileType": ".cpp",
            "linesAdded": 0,
            "linesRemoved": 13,
            "projectName": "date",
            "content": {
              "added": [],
              "removed": []
            },
            "duration": 1,
            "language": "cpp"
          },
          {
            "timestamp": "2025-05-03T14:16:31.505Z",
            "fileName": "c:\\Users\\ludov\\Documents\\Code\\C++\\Utilities\\date\\source\\main.cpp",
            "fileType": ".cpp",
            "linesAdded": 0,
            "linesRemoved": 11,
            "projectName": "date",
            "content": {
              "added": [],
              "removed": []
            },
            "duration": 1,
            "language": "cpp"
          },
          {
            "timestamp": "2025-05-03T14:17:33.014Z",
            "fileName": "c:\\Users\\ludov\\Documents\\Code\\C++\\Utilities\\date\\source\\main.cpp",
            "fileType": ".cpp",
            "linesAdded": 0,
            "linesRemoved": 6,
            "projectName": "date",
            "content": {
              "added": [],
              "removed": []
            },
            "duration": 2,
            "language": "cpp"
          },
          {
            "timestamp": "2025-05-03T14:17:36.921Z",
            "fileName": "c:\\Users\\ludov\\Documents\\Code\\C++\\Utilities\\date\\source\\main.cpp",
            "fileType": ".cpp",
            "linesAdded": 0,
            "linesRemoved": 1,
            "projectName": "date",
            "content": {
              "added": [],
              "removed": []
            },
            "duration": 1,
            "language": "cpp"
          },
          {
            "timestamp": "2025-05-03T14:17:39.742Z",
            "fileName": "c:\\Users\\ludov\\Documents\\Code\\C++\\Utilities\\date\\source\\main.cpp",
            "fileType": ".cpp",
            "linesAdded": 0,
            "linesRemoved": 1,
            "projectName": "date",
            "content": {
              "added": [],
              "removed": []
            },
            "duration": 1,
            "language": "cpp"
          },
          {
            "timestamp": "2025-05-03T14:17:43.138Z",
            "fileName": "c:\\Users\\ludov\\Documents\\Code\\C++\\Utilities\\date\\source\\main.cpp",
            "fileType": ".cpp",
            "linesAdded": 0,
            "linesRemoved": 3,
            "projectName": "date",
            "content": {
              "added": [],
              "removed": []
            },
            "duration": 1,
            "language": "cpp"
          },
          {
            "timestamp": "2025-05-03T14:17:53.217Z",
            "fileName": "c:\\Users\\ludov\\Documents\\Code\\C++\\Utilities\\date\\source\\main.cpp",
            "fileType": ".cpp",
            "linesAdded": 0,
            "linesRemoved": 1,
            "projectName": "date",
            "content": {
              "added": [],
              "removed": []
            },
            "duration": 1,
            "language": "cpp"
          },
          {
            "timestamp": "2025-05-03T14:20:27.692Z",
            "fileName": "c:\\Users\\ludov\\Documents\\Code\\C++\\Utilities\\date\\source\\main.cpp",
            "fileType": ".cpp",
            "linesAdded": 0,
            "linesRemoved": 7,
            "projectName": "date",
            "content": {
              "added": [],
              "removed": []
            },
            "duration": 1,
            "language": "cpp"
          },
          {
            "timestamp": "2025-05-03T14:20:32.208Z",
            "fileName": "c:\\Users\\ludov\\Documents\\Code\\C++\\Utilities\\date\\source\\main.cpp",
            "fileType": ".cpp",
            "linesAdded": 0,
            "linesRemoved": 2,
            "projectName": "date",
            "content": {
              "added": [],
              "removed": []
            },
            "duration": 1,
            "language": "cpp"
          },
          {
            "timestamp": "2025-05-03T14:22:29.478Z",
            "fileName": "c:\\Users\\ludov\\Documents\\Code\\C++\\Utilities\\date\\source\\main.cpp",
            "fileType": ".cpp",
            "linesAdded": 1,
            "linesRemoved": 0,
            "projectName": "date",
            "content": {
              "added": [],
              "removed": []
            },
            "duration": 1,
            "language": "cpp"
          },
          {
            "timestamp": "2025-05-03T14:22:32.204Z",
            "fileName": "c:\\Users\\ludov\\Documents\\Code\\C++\\Utilities\\date\\source\\main.cpp",
            "fileType": ".cpp",
            "linesAdded": 2,
            "linesRemoved": 0,
            "projectName": "date",
            "content": {
              "added": [],
              "removed": []
            },
            "duration": 1,
            "language": "cpp"
          },
          {
            "timestamp": "2025-05-03T14:22:42.512Z",
            "fileName": "c:\\Users\\ludov\\Documents\\Code\\C++\\Utilities\\date\\source\\main.cpp",
            "fileType": ".cpp",
            "linesAdded": 0,
            "linesRemoved": 2,
            "projectName": "date",
            "content": {
              "added": [],
              "removed": []
            },
            "duration": 1,
            "language": "cpp"
          },
          {
            "timestamp": "2025-05-03T14:22:45.335Z",
            "fileName": "c:\\Users\\ludov\\Documents\\Code\\C++\\Utilities\\date\\source\\main.cpp",
            "fileType": ".cpp",
            "linesAdded": 0,
            "linesRemoved": 1,
            "projectName": "date",
            "content": {
              "added": [],
              "removed": []
            },
            "duration": 1,
            "language": "cpp"
          },
          {
            "timestamp": "2025-05-03T16:58:57.388Z",
            "fileName": "c:\\Users\\ludov\\Documents\\Code\\C++\\Utilities\\date\\source\\main.cpp",
            "fileType": ".cpp",
            "linesAdded": 87,
            "linesRemoved": 0,
            "projectName": "date",
            "content": {
              "added": [],
              "removed": []
            },
            "duration": 0,
            "language": "cpp"
          },
          {
            "timestamp": "2025-05-03T17:11:23.688Z",
            "fileName": "c:\\Users\\ludov\\Documents\\Code\\C++\\Utilities\\date\\source\\main.cpp",
            "fileType": ".cpp",
            "linesAdded": 0,
            "linesRemoved": 1,
            "projectName": "date",
            "content": {
              "added": [],
              "removed": []
            },
            "duration": 2,
            "language": "cpp"
          }
        ],
        "c:\\Users\\ludov\\Documents\\Code\\C++\\Utilities\\date\\include\\printer.hpp": [
          {
            "timestamp": "2025-05-02T22:00:33.775Z",
            "fileName": "c:\\Users\\ludov\\Documents\\Code\\C++\\Utilities\\date\\include\\printer.hpp",
            "fileType": ".hpp",
            "linesAdded": 15,
            "linesRemoved": 0,
            "projectName": "date",
            "content": {
              "added": [],
              "removed": []
            },
            "duration": 2,
            "language": "hpp"
          },
          {
            "timestamp": "2025-05-02T22:00:34.790Z",
            "fileName": "c:\\Users\\ludov\\Documents\\Code\\C++\\Utilities\\date\\include\\printer.hpp",
            "fileType": ".hpp",
            "linesAdded": 1,
            "linesRemoved": 0,
            "projectName": "date",
            "content": {
              "added": [],
              "removed": []
            },
            "duration": 1,
            "language": "hpp"
          },
          {
            "timestamp": "2025-05-02T22:00:45.190Z",
            "fileName": "c:\\Users\\ludov\\Documents\\Code\\C++\\Utilities\\date\\include\\printer.hpp",
            "fileType": ".hpp",
            "linesAdded": 1,
            "linesRemoved": 0,
            "projectName": "date",
            "content": {
              "added": [],
              "removed": []
            },
            "duration": 1,
            "language": "hpp"
          },
          {
            "timestamp": "2025-05-03T13:58:12.386Z",
            "fileName": "c:\\Users\\ludov\\Documents\\Code\\C++\\Utilities\\date\\include\\printer.hpp",
            "fileType": ".hpp",
            "linesAdded": 17,
            "linesRemoved": 0,
            "projectName": "date",
            "content": {
              "added": [],
              "removed": []
            },
            "duration": 1,
            "language": "hpp"
          },
          {
            "timestamp": "2025-05-03T13:58:14.439Z",
            "fileName": "c:\\Users\\ludov\\Documents\\Code\\C++\\Utilities\\date\\include\\printer.hpp",
            "fileType": ".hpp",
            "linesAdded": 1,
            "linesRemoved": 0,
            "projectName": "date",
            "content": {
              "added": [],
              "removed": []
            },
            "duration": 1,
            "language": "hpp"
          },
          {
            "timestamp": "2025-05-03T13:58:17.309Z",
            "fileName": "c:\\Users\\ludov\\Documents\\Code\\C++\\Utilities\\date\\include\\printer.hpp",
            "fileType": ".hpp",
            "linesAdded": 1,
            "linesRemoved": 0,
            "projectName": "date",
            "content": {
              "added": [],
              "removed": []
            },
            "duration": 1,
            "language": "hpp"
          },
          {
            "timestamp": "2025-05-03T13:58:22.492Z",
            "fileName": "c:\\Users\\ludov\\Documents\\Code\\C++\\Utilities\\date\\include\\printer.hpp",
            "fileType": ".hpp",
            "linesAdded": 1,
            "linesRemoved": 0,
            "projectName": "date",
            "content": {
              "added": [],
              "removed": []
            },
            "duration": 1,
            "language": "hpp"
          },
          {
            "timestamp": "2025-05-03T13:59:01.379Z",
            "fileName": "c:\\Users\\ludov\\Documents\\Code\\C++\\Utilities\\date\\include\\printer.hpp",
            "fileType": ".hpp",
            "linesAdded": 1,
            "linesRemoved": 0,
            "projectName": "date",
            "content": {
              "added": [],
              "removed": []
            },
            "duration": 1,
            "language": "hpp"
          },
          {
            "timestamp": "2025-05-03T14:10:50.333Z",
            "fileName": "c:\\Users\\ludov\\Documents\\Code\\C++\\Utilities\\date\\include\\printer.hpp",
            "fileType": ".hpp",
            "linesAdded": 1,
            "linesRemoved": 0,
            "projectName": "date",
            "content": {
              "added": [],
              "removed": []
            },
            "duration": 2,
            "language": "hpp"
          },
          {
            "timestamp": "2025-05-03T14:21:18.713Z",
            "fileName": "c:\\Users\\ludov\\Documents\\Code\\C++\\Utilities\\date\\include\\printer.hpp",
            "fileType": ".hpp",
            "linesAdded": 1,
            "linesRemoved": 0,
            "projectName": "date",
            "content": {
              "added": [],
              "removed": []
            },
            "duration": 1,
            "language": "hpp"
          },
          {
            "timestamp": "2025-05-03T14:23:42.153Z",
            "fileName": "c:\\Users\\ludov\\Documents\\Code\\C++\\Utilities\\date\\include\\printer.hpp",
            "fileType": ".hpp",
            "linesAdded": 24,
            "linesRemoved": 0,
            "projectName": "date",
            "content": {
              "added": [],
              "removed": []
            },
            "duration": 1,
            "language": "hpp"
          },
          {
            "timestamp": "2025-05-03T14:23:47.465Z",
            "fileName": "c:\\Users\\ludov\\Documents\\Code\\C++\\Utilities\\date\\include\\printer.hpp",
            "fileType": ".hpp",
            "linesAdded": 1,
            "linesRemoved": 0,
            "projectName": "date",
            "content": {
              "added": [],
              "removed": []
            },
            "duration": 1,
            "language": "hpp"
          }
        ],
        "c:\\Users\\ludov\\Documents\\Code\\C++\\Utilities\\date\\source\\printer.cpp": [
          {
            "timestamp": "2025-05-02T22:01:06.042Z",
            "fileName": "c:\\Users\\ludov\\Documents\\Code\\C++\\Utilities\\date\\source\\printer.cpp",
            "fileType": ".cpp",
            "linesAdded": 29,
            "linesRemoved": 0,
            "projectName": "date",
            "content": {
              "added": [],
              "removed": []
            },
            "duration": 1,
            "language": "cpp"
          },
          {
            "timestamp": "2025-05-02T22:01:07.708Z",
            "fileName": "c:\\Users\\ludov\\Documents\\Code\\C++\\Utilities\\date\\source\\printer.cpp",
            "fileType": ".cpp",
            "linesAdded": 3,
            "linesRemoved": 0,
            "projectName": "date",
            "content": {
              "added": [],
              "removed": []
            },
            "duration": 1,
            "language": "cpp"
          },
          {
            "timestamp": "2025-05-02T22:01:13.325Z",
            "fileName": "c:\\Users\\ludov\\Documents\\Code\\C++\\Utilities\\date\\source\\printer.cpp",
            "fileType": ".cpp",
            "linesAdded": 2,
            "linesRemoved": 0,
            "projectName": "date",
            "content": {
              "added": [],
              "removed": []
            },
            "duration": 1,
            "language": "cpp"
          },
          {
            "timestamp": "2025-05-02T22:01:16.302Z",
            "fileName": "c:\\Users\\ludov\\Documents\\Code\\C++\\Utilities\\date\\source\\printer.cpp",
            "fileType": ".cpp",
            "linesAdded": 4,
            "linesRemoved": 0,
            "projectName": "date",
            "content": {
              "added": [],
              "removed": []
            },
            "duration": 1,
            "language": "cpp"
          },
          {
            "timestamp": "2025-05-02T22:01:18.911Z",
            "fileName": "c:\\Users\\ludov\\Documents\\Code\\C++\\Utilities\\date\\source\\printer.cpp",
            "fileType": ".cpp",
            "linesAdded": 2,
            "linesRemoved": 0,
            "projectName": "date",
            "content": {
              "added": [],
              "removed": []
            },
            "duration": 1,
            "language": "cpp"
          },
          {
            "timestamp": "2025-05-02T22:01:21.994Z",
            "fileName": "c:\\Users\\ludov\\Documents\\Code\\C++\\Utilities\\date\\source\\printer.cpp",
            "fileType": ".cpp",
            "linesAdded": 0,
            "linesRemoved": 1,
            "projectName": "date",
            "content": {
              "added": [],
              "removed": []
            },
            "duration": 1,
            "language": "cpp"
          },
          {
            "timestamp": "2025-05-03T13:58:36.322Z",
            "fileName": "c:\\Users\\ludov\\Documents\\Code\\C++\\Utilities\\date\\source\\printer.cpp",
            "fileType": ".cpp",
            "linesAdded": 39,
            "linesRemoved": 0,
            "projectName": "date",
            "content": {
              "added": [],
              "removed": []
            },
            "duration": 1,
            "language": "cpp"
          },
          {
            "timestamp": "2025-05-03T13:58:38.996Z",
            "fileName": "c:\\Users\\ludov\\Documents\\Code\\C++\\Utilities\\date\\source\\printer.cpp",
            "fileType": ".cpp",
            "linesAdded": 2,
            "linesRemoved": 0,
            "projectName": "date",
            "content": {
              "added": [],
              "removed": []
            },
            "duration": 1,
            "language": "cpp"
          },
          {
            "timestamp": "2025-05-03T13:58:46.374Z",
            "fileName": "c:\\Users\\ludov\\Documents\\Code\\C++\\Utilities\\date\\source\\printer.cpp",
            "fileType": ".cpp",
            "linesAdded": 1,
            "linesRemoved": 0,
            "projectName": "date",
            "content": {
              "added": [],
              "removed": []
            },
            "duration": 1,
            "language": "cpp"
          },
          {
            "timestamp": "2025-05-03T13:58:54.701Z",
            "fileName": "c:\\Users\\ludov\\Documents\\Code\\C++\\Utilities\\date\\source\\printer.cpp",
            "fileType": ".cpp",
            "linesAdded": 1,
            "linesRemoved": 0,
            "projectName": "date",
            "content": {
              "added": [],
              "removed": []
            },
            "duration": 1,
            "language": "cpp"
          },
          {
            "timestamp": "2025-05-03T13:59:27.000Z",
            "fileName": "c:\\Users\\ludov\\Documents\\Code\\C++\\Utilities\\date\\source\\printer.cpp",
            "fileType": ".cpp",
            "linesAdded": 2,
            "linesRemoved": 0,
            "projectName": "date",
            "content": {
              "added": [],
              "removed": []
            },
            "duration": 1,
            "language": "cpp"
          },
          {
            "timestamp": "2025-05-03T13:59:54.697Z",
            "fileName": "c:\\Users\\ludov\\Documents\\Code\\C++\\Utilities\\date\\source\\printer.cpp",
            "fileType": ".cpp",
            "linesAdded": 2,
            "linesRemoved": 0,
            "projectName": "date",
            "content": {
              "added": [],
              "removed": []
            },
            "duration": 1,
            "language": "cpp"
          },
          {
            "timestamp": "2025-05-03T14:00:00.355Z",
            "fileName": "c:\\Users\\ludov\\Documents\\Code\\C++\\Utilities\\date\\source\\printer.cpp",
            "fileType": ".cpp",
            "linesAdded": 0,
            "linesRemoved": 2,
            "projectName": "date",
            "content": {
              "added": [],
              "removed": []
            },
            "duration": 1,
            "language": "cpp"
          },
          {
            "timestamp": "2025-05-03T14:00:21.779Z",
            "fileName": "c:\\Users\\ludov\\Documents\\Code\\C++\\Utilities\\date\\source\\printer.cpp",
            "fileType": ".cpp",
            "linesAdded": 0,
            "linesRemoved": 1,
            "projectName": "date",
            "content": {
              "added": [],
              "removed": []
            },
            "duration": 1,
            "language": "cpp"
          },
          {
            "timestamp": "2025-05-03T14:00:29.527Z",
            "fileName": "c:\\Users\\ludov\\Documents\\Code\\C++\\Utilities\\date\\source\\printer.cpp",
            "fileType": ".cpp",
            "linesAdded": 0,
            "linesRemoved": 2,
            "projectName": "date",
            "content": {
              "added": [],
              "removed": []
            },
            "duration": 1,
            "language": "cpp"
          },
          {
            "timestamp": "2025-05-03T14:02:03.582Z",
            "fileName": "c:\\Users\\ludov\\Documents\\Code\\C++\\Utilities\\date\\source\\printer.cpp",
            "fileType": ".cpp",
            "linesAdded": 2,
            "linesRemoved": 0,
            "projectName": "date",
            "content": {
              "added": [],
              "removed": []
            },
            "duration": 1,
            "language": "cpp"
          },
          {
            "timestamp": "2025-05-03T14:02:18.917Z",
            "fileName": "c:\\Users\\ludov\\Documents\\Code\\C++\\Utilities\\date\\source\\printer.cpp",
            "fileType": ".cpp",
            "linesAdded": 1,
            "linesRemoved": 0,
            "projectName": "date",
            "content": {
              "added": [],
              "removed": []
            },
            "duration": 1,
            "language": "cpp"
          },
          {
            "timestamp": "2025-05-03T14:02:21.899Z",
            "fileName": "c:\\Users\\ludov\\Documents\\Code\\C++\\Utilities\\date\\source\\printer.cpp",
            "fileType": ".cpp",
            "linesAdded": 1,
            "linesRemoved": 0,
            "projectName": "date",
            "content": {
              "added": [],
              "removed": []
            },
            "duration": 1,
            "language": "cpp"
          },
          {
            "timestamp": "2025-05-03T14:02:47.120Z",
            "fileName": "c:\\Users\\ludov\\Documents\\Code\\C++\\Utilities\\date\\source\\printer.cpp",
            "fileType": ".cpp",
            "linesAdded": 1,
            "linesRemoved": 0,
            "projectName": "date",
            "content": {
              "added": [],
              "removed": []
            },
            "duration": 1,
            "language": "cpp"
          },
          {
            "timestamp": "2025-05-03T14:02:55.455Z",
            "fileName": "c:\\Users\\ludov\\Documents\\Code\\C++\\Utilities\\date\\source\\printer.cpp",
            "fileType": ".cpp",
            "linesAdded": 0,
            "linesRemoved": 1,
            "projectName": "date",
            "content": {
              "added": [],
              "removed": []
            },
            "duration": 1,
            "language": "cpp"
          },
          {
            "timestamp": "2025-05-03T14:03:09.299Z",
            "fileName": "c:\\Users\\ludov\\Documents\\Code\\C++\\Utilities\\date\\source\\printer.cpp",
            "fileType": ".cpp",
            "linesAdded": 1,
            "linesRemoved": 0,
            "projectName": "date",
            "content": {
              "added": [],
              "removed": []
            },
            "duration": 1,
            "language": "cpp"
          },
          {
            "timestamp": "2025-05-03T14:03:19.203Z",
            "fileName": "c:\\Users\\ludov\\Documents\\Code\\C++\\Utilities\\date\\source\\printer.cpp",
            "fileType": ".cpp",
            "linesAdded": 0,
            "linesRemoved": 1,
            "projectName": "date",
            "content": {
              "added": [],
              "removed": []
            },
            "duration": 1,
            "language": "cpp"
          },
          {
            "timestamp": "2025-05-03T14:04:01.222Z",
            "fileName": "c:\\Users\\ludov\\Documents\\Code\\C++\\Utilities\\date\\source\\printer.cpp",
            "fileType": ".cpp",
            "linesAdded": 0,
            "linesRemoved": 1,
            "projectName": "date",
            "content": {
              "added": [],
              "removed": []
            },
            "duration": 1,
            "language": "cpp"
          },
          {
            "timestamp": "2025-05-03T14:11:02.084Z",
            "fileName": "c:\\Users\\ludov\\Documents\\Code\\C++\\Utilities\\date\\source\\printer.cpp",
            "fileType": ".cpp",
            "linesAdded": 2,
            "linesRemoved": 0,
            "projectName": "date",
            "content": {
              "added": [],
              "removed": []
            },
            "duration": 1,
            "language": "cpp"
          },
          {
            "timestamp": "2025-05-03T14:11:07.167Z",
            "fileName": "c:\\Users\\ludov\\Documents\\Code\\C++\\Utilities\\date\\source\\printer.cpp",
            "fileType": ".cpp",
            "linesAdded": 1,
            "linesRemoved": 0,
            "projectName": "date",
            "content": {
              "added": [],
              "removed": []
            },
            "duration": 1,
            "language": "cpp"
          },
          {
            "timestamp": "2025-05-03T14:11:09.125Z",
            "fileName": "c:\\Users\\ludov\\Documents\\Code\\C++\\Utilities\\date\\source\\printer.cpp",
            "fileType": ".cpp",
            "linesAdded": 2,
            "linesRemoved": 0,
            "projectName": "date",
            "content": {
              "added": [],
              "removed": []
            },
            "duration": 1,
            "language": "cpp"
          },
          {
            "timestamp": "2025-05-03T14:12:38.401Z",
            "fileName": "c:\\Users\\ludov\\Documents\\Code\\C++\\Utilities\\date\\source\\printer.cpp",
            "fileType": ".cpp",
            "linesAdded": 1,
            "linesRemoved": 0,
            "projectName": "date",
            "content": {
              "added": [],
              "removed": []
            },
            "duration": 2,
            "language": "cpp"
          },
          {
            "timestamp": "2025-05-03T14:14:01.173Z",
            "fileName": "c:\\Users\\ludov\\Documents\\Code\\C++\\Utilities\\date\\source\\printer.cpp",
            "fileType": ".cpp",
            "linesAdded": 1,
            "linesRemoved": 0,
            "projectName": "date",
            "content": {
              "added": [],
              "removed": []
            },
            "duration": 1,
            "language": "cpp"
          },
          {
            "timestamp": "2025-05-03T14:14:17.949Z",
            "fileName": "c:\\Users\\ludov\\Documents\\Code\\C++\\Utilities\\date\\source\\printer.cpp",
            "fileType": ".cpp",
            "linesAdded": 1,
            "linesRemoved": 0,
            "projectName": "date",
            "content": {
              "added": [],
              "removed": []
            },
            "duration": 1,
            "language": "cpp"
          },
          {
            "timestamp": "2025-05-03T14:15:02.103Z",
            "fileName": "c:\\Users\\ludov\\Documents\\Code\\C++\\Utilities\\date\\source\\printer.cpp",
            "fileType": ".cpp",
            "linesAdded": 1,
            "linesRemoved": 0,
            "projectName": "date",
            "content": {
              "added": [],
              "removed": []
            },
            "duration": 1,
            "language": "cpp"
          },
          {
            "timestamp": "2025-05-03T14:15:22.497Z",
            "fileName": "c:\\Users\\ludov\\Documents\\Code\\C++\\Utilities\\date\\source\\printer.cpp",
            "fileType": ".cpp",
            "linesAdded": 1,
            "linesRemoved": 0,
            "projectName": "date",
            "content": {
              "added": [],
              "removed": []
            },
            "duration": 1,
            "language": "cpp"
          },
          {
            "timestamp": "2025-05-03T14:21:53.710Z",
            "fileName": "c:\\Users\\ludov\\Documents\\Code\\C++\\Utilities\\date\\source\\printer.cpp",
            "fileType": ".cpp",
            "linesAdded": 2,
            "linesRemoved": 0,
            "projectName": "date",
            "content": {
              "added": [],
              "removed": []
            },
            "duration": 1,
            "language": "cpp"
          },
          {
            "timestamp": "2025-05-03T14:22:00.217Z",
            "fileName": "c:\\Users\\ludov\\Documents\\Code\\C++\\Utilities\\date\\source\\printer.cpp",
            "fileType": ".cpp",
            "linesAdded": 1,
            "linesRemoved": 0,
            "projectName": "date",
            "content": {
              "added": [],
              "removed": []
            },
            "duration": 1,
            "language": "cpp"
          },
          {
            "timestamp": "2025-05-03T14:22:01.909Z",
            "fileName": "c:\\Users\\ludov\\Documents\\Code\\C++\\Utilities\\date\\source\\printer.cpp",
            "fileType": ".cpp",
            "linesAdded": 2,
            "linesRemoved": 0,
            "projectName": "date",
            "content": {
              "added": [],
              "removed": []
            },
            "duration": 1,
            "language": "cpp"
          },
          {
            "timestamp": "2025-05-03T14:22:16.432Z",
            "fileName": "c:\\Users\\ludov\\Documents\\Code\\C++\\Utilities\\date\\source\\printer.cpp",
            "fileType": ".cpp",
            "linesAdded": 7,
            "linesRemoved": 0,
            "projectName": "date",
            "content": {
              "added": [],
              "removed": []
            },
            "duration": 1,
            "language": "cpp"
          },
          {
            "timestamp": "2025-05-03T14:25:08.068Z",
            "fileName": "c:\\Users\\ludov\\Documents\\Code\\C++\\Utilities\\date\\source\\printer.cpp",
            "fileType": ".cpp",
            "linesAdded": 2,
            "linesRemoved": 0,
            "projectName": "date",
            "content": {
              "added": [],
              "removed": []
            },
            "duration": 1,
            "language": "cpp"
          },
          {
            "timestamp": "2025-05-03T14:25:09.189Z",
            "fileName": "c:\\Users\\ludov\\Documents\\Code\\C++\\Utilities\\date\\source\\printer.cpp",
            "fileType": ".cpp",
            "linesAdded": 23,
            "linesRemoved": 0,
            "projectName": "date",
            "content": {
              "added": [],
              "removed": []
            },
            "duration": 1,
            "language": "cpp"
          }
        ],
        "c:\\Users\\ludov\\Documents\\Code\\C++\\Utilities\\date\\include\\clock.hpp": [
          {
            "timestamp": "2025-05-02T22:02:09.993Z",
            "fileName": "c:\\Users\\ludov\\Documents\\Code\\C++\\Utilities\\date\\include\\clock.hpp",
            "fileType": ".hpp",
            "linesAdded": 2,
            "linesRemoved": 0,
            "projectName": "date",
            "content": {
              "added": [],
              "removed": []
            },
            "duration": 1,
            "language": "hpp"
          },
          {
            "timestamp": "2025-05-02T22:02:12.292Z",
            "fileName": "c:\\Users\\ludov\\Documents\\Code\\C++\\Utilities\\date\\include\\clock.hpp",
            "fileType": ".hpp",
            "linesAdded": 0,
            "linesRemoved": 1,
            "projectName": "date",
            "content": {
              "added": [],
              "removed": []
            },
            "duration": 1,
            "language": "hpp"
          },
          {
            "timestamp": "2025-05-02T22:05:51.750Z",
            "fileName": "c:\\Users\\ludov\\Documents\\Code\\C++\\Utilities\\date\\include\\clock.hpp",
            "fileType": ".hpp",
            "linesAdded": 1,
            "linesRemoved": 0,
            "projectName": "date",
            "content": {
              "added": [],
              "removed": []
            },
            "duration": 2,
            "language": "hpp"
          },
          {
            "timestamp": "2025-05-02T22:05:57.168Z",
            "fileName": "c:\\Users\\ludov\\Documents\\Code\\C++\\Utilities\\date\\include\\clock.hpp",
            "fileType": ".hpp",
            "linesAdded": 2,
            "linesRemoved": 0,
            "projectName": "date",
            "content": {
              "added": [],
              "removed": []
            },
            "duration": 1,
            "language": "hpp"
          },
          {
            "timestamp": "2025-05-02T22:06:00.900Z",
            "fileName": "c:\\Users\\ludov\\Documents\\Code\\C++\\Utilities\\date\\include\\clock.hpp",
            "fileType": ".hpp",
            "linesAdded": 0,
            "linesRemoved": 2,
            "projectName": "date",
            "content": {
              "added": [],
              "removed": []
            },
            "duration": 1,
            "language": "hpp"
          },
          {
            "timestamp": "2025-05-02T22:06:02.058Z",
            "fileName": "c:\\Users\\ludov\\Documents\\Code\\C++\\Utilities\\date\\include\\clock.hpp",
            "fileType": ".hpp",
            "linesAdded": 2,
            "linesRemoved": 0,
            "projectName": "date",
            "content": {
              "added": [],
              "removed": []
            },
            "duration": 1,
            "language": "hpp"
          },
          {
            "timestamp": "2025-05-02T22:06:04.989Z",
            "fileName": "c:\\Users\\ludov\\Documents\\Code\\C++\\Utilities\\date\\include\\clock.hpp",
            "fileType": ".hpp",
            "linesAdded": 1,
            "linesRemoved": 0,
            "projectName": "date",
            "content": {
              "added": [],
              "removed": []
            },
            "duration": 1,
            "language": "hpp"
          },
          {
            "timestamp": "2025-05-02T22:09:08.729Z",
            "fileName": "c:\\Users\\ludov\\Documents\\Code\\C++\\Utilities\\date\\include\\clock.hpp",
            "fileType": ".hpp",
            "linesAdded": 1,
            "linesRemoved": 0,
            "projectName": "date",
            "content": {
              "added": [],
              "removed": []
            },
            "duration": 4,
            "language": "hpp"
          },
          {
            "timestamp": "2025-05-02T22:09:45.245Z",
            "fileName": "c:\\Users\\ludov\\Documents\\Code\\C++\\Utilities\\date\\include\\clock.hpp",
            "fileType": ".hpp",
            "linesAdded": 1,
            "linesRemoved": 0,
            "projectName": "date",
            "content": {
              "added": [],
              "removed": []
            },
            "duration": 1,
            "language": "hpp"
          },
          {
            "timestamp": "2025-05-02T22:10:30.599Z",
            "fileName": "c:\\Users\\ludov\\Documents\\Code\\C++\\Utilities\\date\\include\\clock.hpp",
            "fileType": ".hpp",
            "linesAdded": 1,
            "linesRemoved": 0,
            "projectName": "date",
            "content": {
              "added": [],
              "removed": []
            },
            "duration": 1,
            "language": "hpp"
          },
          {
            "timestamp": "2025-05-03T13:42:04.965Z",
            "fileName": "c:\\Users\\ludov\\Documents\\Code\\C++\\Utilities\\date\\include\\clock.hpp",
            "fileType": ".hpp",
            "linesAdded": 27,
            "linesRemoved": 0,
            "projectName": "date",
            "content": {
              "added": [],
              "removed": []
            },
            "duration": 1,
            "language": "hpp"
          },
          {
            "timestamp": "2025-05-03T13:42:54.850Z",
            "fileName": "c:\\Users\\ludov\\Documents\\Code\\C++\\Utilities\\date\\include\\clock.hpp",
            "fileType": ".hpp",
            "linesAdded": 1,
            "linesRemoved": 0,
            "projectName": "date",
            "content": {
              "added": [],
              "removed": []
            },
            "duration": 1,
            "language": "hpp"
          },
          {
            "timestamp": "2025-05-03T13:43:31.767Z",
            "fileName": "c:\\Users\\ludov\\Documents\\Code\\C++\\Utilities\\date\\include\\clock.hpp",
            "fileType": ".hpp",
            "linesAdded": 0,
            "linesRemoved": 1,
            "projectName": "date",
            "content": {
              "added": [],
              "removed": []
            },
            "duration": 1,
            "language": "hpp"
          },
          {
            "timestamp": "2025-05-03T13:53:37.534Z",
            "fileName": "c:\\Users\\ludov\\Documents\\Code\\C++\\Utilities\\date\\include\\clock.hpp",
            "fileType": ".hpp",
            "linesAdded": 1,
            "linesRemoved": 0,
            "projectName": "date",
            "content": {
              "added": [],
              "removed": []
            },
            "duration": 1,
            "language": "hpp"
          },
          {
            "timestamp": "2025-05-03T14:23:59.059Z",
            "fileName": "c:\\Users\\ludov\\Documents\\Code\\C++\\Utilities\\date\\include\\clock.hpp",
            "fileType": ".hpp",
            "linesAdded": 24,
            "linesRemoved": 0,
            "projectName": "date",
            "content": {
              "added": [],
              "removed": []
            },
            "duration": 1,
            "language": "hpp"
          },
          {
            "timestamp": "2025-05-03T14:24:01.657Z",
            "fileName": "c:\\Users\\ludov\\Documents\\Code\\C++\\Utilities\\date\\include\\clock.hpp",
            "fileType": ".hpp",
            "linesAdded": 1,
            "linesRemoved": 0,
            "projectName": "date",
            "content": {
              "added": [],
              "removed": []
            },
            "duration": 1,
            "language": "hpp"
          }
        ],
        "c:\\Users\\ludov\\Documents\\Code\\C++\\Utilities\\date\\include\\formatter.hpp": [
          {
            "timestamp": "2025-05-02T22:03:22.642Z",
            "fileName": "c:\\Users\\ludov\\Documents\\Code\\C++\\Utilities\\date\\include\\formatter.hpp",
            "fileType": ".hpp",
            "linesAdded": 16,
            "linesRemoved": 0,
            "projectName": "date",
            "content": {
              "added": [],
              "removed": []
            },
            "duration": 2,
            "language": "hpp"
          },
          {
            "timestamp": "2025-05-02T22:03:26.436Z",
            "fileName": "c:\\Users\\ludov\\Documents\\Code\\C++\\Utilities\\date\\include\\formatter.hpp",
            "fileType": ".hpp",
            "linesAdded": 1,
            "linesRemoved": 0,
            "projectName": "date",
            "content": {
              "added": [],
              "removed": []
            },
            "duration": 1,
            "language": "hpp"
          },
          {
            "timestamp": "2025-05-02T22:04:08.202Z",
            "fileName": "c:\\Users\\ludov\\Documents\\Code\\C++\\Utilities\\date\\include\\formatter.hpp",
            "fileType": ".hpp",
            "linesAdded": 0,
            "linesRemoved": 1,
            "projectName": "date",
            "content": {
              "added": [],
              "removed": []
            },
            "duration": 1,
            "language": "hpp"
          },
          {
            "timestamp": "2025-05-03T14:20:09.234Z",
            "fileName": "c:\\Users\\ludov\\Documents\\Code\\C++\\Utilities\\date\\include\\formatter.hpp",
            "fileType": ".hpp",
            "linesAdded": 16,
            "linesRemoved": 0,
            "projectName": "date",
            "content": {
              "added": [],
              "removed": []
            },
            "duration": 1,
            "language": "hpp"
          },
          {
            "timestamp": "2025-05-03T14:24:33.856Z",
            "fileName": "c:\\Users\\ludov\\Documents\\Code\\C++\\Utilities\\date\\include\\formatter.hpp",
            "fileType": ".hpp",
            "linesAdded": 25,
            "linesRemoved": 0,
            "projectName": "date",
            "content": {
              "added": [],
              "removed": []
            },
            "duration": 1,
            "language": "hpp"
          },
          {
            "timestamp": "2025-05-03T17:13:17.263Z",
            "fileName": "c:\\Users\\ludov\\Documents\\Code\\C++\\Utilities\\date\\include\\formatter.hpp",
            "fileType": ".hpp",
            "linesAdded": 41,
            "linesRemoved": 0,
            "projectName": "date",
            "content": {
              "added": [],
              "removed": []
            },
            "duration": 2,
            "language": "hpp"
          },
          {
            "timestamp": "2025-05-03T17:13:18.275Z",
            "fileName": "c:\\Users\\ludov\\Documents\\Code\\C++\\Utilities\\date\\include\\formatter.hpp",
            "fileType": ".hpp",
            "linesAdded": 1,
            "linesRemoved": 0,
            "projectName": "date",
            "content": {
              "added": [],
              "removed": []
            },
            "duration": 1,
            "language": "hpp"
          }
        ],
        "c:\\Users\\ludov\\Documents\\Code\\C++\\Utilities\\date\\source\\formatter.cpp": [
          {
            "timestamp": "2025-05-02T22:03:31.163Z",
            "fileName": "c:\\Users\\ludov\\Documents\\Code\\C++\\Utilities\\date\\source\\formatter.cpp",
            "fileType": ".cpp",
            "linesAdded": 12,
            "linesRemoved": 0,
            "projectName": "date",
            "content": {
              "added": [],
              "removed": []
            },
            "duration": 1,
            "language": "cpp"
          },
          {
            "timestamp": "2025-05-02T22:03:36.554Z",
            "fileName": "c:\\Users\\ludov\\Documents\\Code\\C++\\Utilities\\date\\source\\formatter.cpp",
            "fileType": ".cpp",
            "linesAdded": 1,
            "linesRemoved": 0,
            "projectName": "date",
            "content": {
              "added": [],
              "removed": []
            },
            "duration": 1,
            "language": "cpp"
          },
          {
            "timestamp": "2025-05-02T22:04:04.716Z",
            "fileName": "c:\\Users\\ludov\\Documents\\Code\\C++\\Utilities\\date\\source\\formatter.cpp",
            "fileType": ".cpp",
            "linesAdded": 0,
            "linesRemoved": 1,
            "projectName": "date",
            "content": {
              "added": [],
              "removed": []
            },
            "duration": 1,
            "language": "cpp"
          },
          {
            "timestamp": "2025-05-03T14:20:05.746Z",
            "fileName": "c:\\Users\\ludov\\Documents\\Code\\C++\\Utilities\\date\\source\\formatter.cpp",
            "fileType": ".cpp",
            "linesAdded": 12,
            "linesRemoved": 0,
            "projectName": "date",
            "content": {
              "added": [],
              "removed": []
            },
            "duration": 3,
            "language": "cpp"
          },
          {
            "timestamp": "2025-05-03T14:20:36.808Z",
            "fileName": "c:\\Users\\ludov\\Documents\\Code\\C++\\Utilities\\date\\source\\formatter.cpp",
            "fileType": ".cpp",
            "linesAdded": 5,
            "linesRemoved": 0,
            "projectName": "date",
            "content": {
              "added": [],
              "removed": []
            },
            "duration": 1,
            "language": "cpp"
          },
          {
            "timestamp": "2025-05-03T14:25:00.726Z",
            "fileName": "c:\\Users\\ludov\\Documents\\Code\\C++\\Utilities\\date\\source\\formatter.cpp",
            "fileType": ".cpp",
            "linesAdded": 25,
            "linesRemoved": 0,
            "projectName": "date",
            "content": {
              "added": [],
              "removed": []
            },
            "duration": 1,
            "language": "cpp"
          },
          {
            "timestamp": "2025-05-03T17:02:15.123Z",
            "fileName": "c:\\Users\\ludov\\Documents\\Code\\C++\\Utilities\\date\\source\\formatter.cpp",
            "fileType": ".cpp",
            "linesAdded": 42,
            "linesRemoved": 0,
            "projectName": "date",
            "content": {
              "added": [],
              "removed": []
            },
            "duration": 4,
            "language": "cpp"
          },
          {
            "timestamp": "2025-05-03T17:02:16.134Z",
            "fileName": "c:\\Users\\ludov\\Documents\\Code\\C++\\Utilities\\date\\source\\formatter.cpp",
            "fileType": ".cpp",
            "linesAdded": 1,
            "linesRemoved": 0,
            "projectName": "date",
            "content": {
              "added": [],
              "removed": []
            },
            "duration": 1,
            "language": "cpp"
          },
          {
            "timestamp": "2025-05-03T17:02:21.027Z",
            "fileName": "c:\\Users\\ludov\\Documents\\Code\\C++\\Utilities\\date\\source\\formatter.cpp",
            "fileType": ".cpp",
            "linesAdded": 2,
            "linesRemoved": 0,
            "projectName": "date",
            "content": {
              "added": [],
              "removed": []
            },
            "duration": 1,
            "language": "cpp"
          },
          {
            "timestamp": "2025-05-03T17:02:55.254Z",
            "fileName": "c:\\Users\\ludov\\Documents\\Code\\C++\\Utilities\\date\\source\\formatter.cpp",
            "fileType": ".cpp",
            "linesAdded": 1,
            "linesRemoved": 0,
            "projectName": "date",
            "content": {
              "added": [],
              "removed": []
            },
            "duration": 1,
            "language": "cpp"
          },
          {
            "timestamp": "2025-05-03T17:02:57.734Z",
            "fileName": "c:\\Users\\ludov\\Documents\\Code\\C++\\Utilities\\date\\source\\formatter.cpp",
            "fileType": ".cpp",
            "linesAdded": 0,
            "linesRemoved": 1,
            "projectName": "date",
            "content": {
              "added": [],
              "removed": []
            },
            "duration": 1,
            "language": "cpp"
          },
          {
            "timestamp": "2025-05-03T17:03:13.878Z",
            "fileName": "c:\\Users\\ludov\\Documents\\Code\\C++\\Utilities\\date\\source\\formatter.cpp",
            "fileType": ".cpp",
            "linesAdded": 1,
            "linesRemoved": 0,
            "projectName": "date",
            "content": {
              "added": [],
              "removed": []
            },
            "duration": 1,
            "language": "cpp"
          },
          {
            "timestamp": "2025-05-03T17:03:21.105Z",
            "fileName": "c:\\Users\\ludov\\Documents\\Code\\C++\\Utilities\\date\\source\\formatter.cpp",
            "fileType": ".cpp",
            "linesAdded": 2,
            "linesRemoved": 0,
            "projectName": "date",
            "content": {
              "added": [],
              "removed": []
            },
            "duration": 1,
            "language": "cpp"
          },
          {
            "timestamp": "2025-05-03T17:03:47.061Z",
            "fileName": "c:\\Users\\ludov\\Documents\\Code\\C++\\Utilities\\date\\source\\formatter.cpp",
            "fileType": ".cpp",
            "linesAdded": 1,
            "linesRemoved": 0,
            "projectName": "date",
            "content": {
              "added": [],
              "removed": []
            },
            "duration": 1,
            "language": "cpp"
          },
          {
            "timestamp": "2025-05-03T17:03:49.524Z",
            "fileName": "c:\\Users\\ludov\\Documents\\Code\\C++\\Utilities\\date\\source\\formatter.cpp",
            "fileType": ".cpp",
            "linesAdded": 2,
            "linesRemoved": 0,
            "projectName": "date",
            "content": {
              "added": [],
              "removed": []
            },
            "duration": 1,
            "language": "cpp"
          },
          {
            "timestamp": "2025-05-03T17:04:20.320Z",
            "fileName": "c:\\Users\\ludov\\Documents\\Code\\C++\\Utilities\\date\\source\\formatter.cpp",
            "fileType": ".cpp",
            "linesAdded": 1,
            "linesRemoved": 0,
            "projectName": "date",
            "content": {
              "added": [],
              "removed": []
            },
            "duration": 1,
            "language": "cpp"
          },
          {
            "timestamp": "2025-05-03T17:04:39.904Z",
            "fileName": "c:\\Users\\ludov\\Documents\\Code\\C++\\Utilities\\date\\source\\formatter.cpp",
            "fileType": ".cpp",
            "linesAdded": 1,
            "linesRemoved": 0,
            "projectName": "date",
            "content": {
              "added": [],
              "removed": []
            },
            "duration": 1,
            "language": "cpp"
          },
          {
            "timestamp": "2025-05-03T17:04:44.543Z",
            "fileName": "c:\\Users\\ludov\\Documents\\Code\\C++\\Utilities\\date\\source\\formatter.cpp",
            "fileType": ".cpp",
            "linesAdded": 1,
            "linesRemoved": 0,
            "projectName": "date",
            "content": {
              "added": [],
              "removed": []
            },
            "duration": 1,
            "language": "cpp"
          },
          {
            "timestamp": "2025-05-03T17:05:02.788Z",
            "fileName": "c:\\Users\\ludov\\Documents\\Code\\C++\\Utilities\\date\\source\\formatter.cpp",
            "fileType": ".cpp",
            "linesAdded": 1,
            "linesRemoved": 0,
            "projectName": "date",
            "content": {
              "added": [],
              "removed": []
            },
            "duration": 1,
            "language": "cpp"
          },
          {
            "timestamp": "2025-05-03T17:05:04.469Z",
            "fileName": "c:\\Users\\ludov\\Documents\\Code\\C++\\Utilities\\date\\source\\formatter.cpp",
            "fileType": ".cpp",
            "linesAdded": 1,
            "linesRemoved": 0,
            "projectName": "date",
            "content": {
              "added": [],
              "removed": []
            },
            "duration": 1,
            "language": "cpp"
          },
          {
            "timestamp": "2025-05-03T17:05:12.894Z",
            "fileName": "c:\\Users\\ludov\\Documents\\Code\\C++\\Utilities\\date\\source\\formatter.cpp",
            "fileType": ".cpp",
            "linesAdded": 1,
            "linesRemoved": 0,
            "projectName": "date",
            "content": {
              "added": [],
              "removed": []
            },
            "duration": 1,
            "language": "cpp"
          },
          {
            "timestamp": "2025-05-03T17:06:01.945Z",
            "fileName": "c:\\Users\\ludov\\Documents\\Code\\C++\\Utilities\\date\\source\\formatter.cpp",
            "fileType": ".cpp",
            "linesAdded": 5,
            "linesRemoved": 0,
            "projectName": "date",
            "content": {
              "added": [],
              "removed": []
            },
            "duration": 1,
            "language": "cpp"
          },
          {
            "timestamp": "2025-05-03T17:06:08.385Z",
            "fileName": "c:\\Users\\ludov\\Documents\\Code\\C++\\Utilities\\date\\source\\formatter.cpp",
            "fileType": ".cpp",
            "linesAdded": 5,
            "linesRemoved": 0,
            "projectName": "date",
            "content": {
              "added": [],
              "removed": []
            },
            "duration": 1,
            "language": "cpp"
          },
          {
            "timestamp": "2025-05-03T17:08:36.286Z",
            "fileName": "c:\\Users\\ludov\\Documents\\Code\\C++\\Utilities\\date\\source\\formatter.cpp",
            "fileType": ".cpp",
            "linesAdded": 1,
            "linesRemoved": 0,
            "projectName": "date",
            "content": {
              "added": [],
              "removed": []
            },
            "duration": 2,
            "language": "cpp"
          },
          {
            "timestamp": "2025-05-03T17:08:47.661Z",
            "fileName": "c:\\Users\\ludov\\Documents\\Code\\C++\\Utilities\\date\\source\\formatter.cpp",
            "fileType": ".cpp",
            "linesAdded": 1,
            "linesRemoved": 0,
            "projectName": "date",
            "content": {
              "added": [],
              "removed": []
            },
            "duration": 1,
            "language": "cpp"
          },
          {
            "timestamp": "2025-05-03T17:08:57.951Z",
            "fileName": "c:\\Users\\ludov\\Documents\\Code\\C++\\Utilities\\date\\source\\formatter.cpp",
            "fileType": ".cpp",
            "linesAdded": 0,
            "linesRemoved": 1,
            "projectName": "date",
            "content": {
              "added": [],
              "removed": []
            },
            "duration": 1,
            "language": "cpp"
          },
          {
            "timestamp": "2025-05-03T17:09:02.555Z",
            "fileName": "c:\\Users\\ludov\\Documents\\Code\\C++\\Utilities\\date\\source\\formatter.cpp",
            "fileType": ".cpp",
            "linesAdded": 0,
            "linesRemoved": 1,
            "projectName": "date",
            "content": {
              "added": [],
              "removed": []
            },
            "duration": 1,
            "language": "cpp"
          },
          {
            "timestamp": "2025-05-03T17:09:29.958Z",
            "fileName": "c:\\Users\\ludov\\Documents\\Code\\C++\\Utilities\\date\\source\\formatter.cpp",
            "fileType": ".cpp",
            "linesAdded": 2,
            "linesRemoved": 0,
            "projectName": "date",
            "content": {
              "added": [],
              "removed": []
            },
            "duration": 1,
            "language": "cpp"
          },
          {
            "timestamp": "2025-05-03T17:09:33.678Z",
            "fileName": "c:\\Users\\ludov\\Documents\\Code\\C++\\Utilities\\date\\source\\formatter.cpp",
            "fileType": ".cpp",
            "linesAdded": 2,
            "linesRemoved": 0,
            "projectName": "date",
            "content": {
              "added": [],
              "removed": []
            },
            "duration": 1,
            "language": "cpp"
          },
          {
            "timestamp": "2025-05-03T17:10:06.577Z",
            "fileName": "c:\\Users\\ludov\\Documents\\Code\\C++\\Utilities\\date\\source\\formatter.cpp",
            "fileType": ".cpp",
            "linesAdded": 0,
            "linesRemoved": 4,
            "projectName": "date",
            "content": {
              "added": [],
              "removed": []
            },
            "duration": 1,
            "language": "cpp"
          },
          {
            "timestamp": "2025-05-03T17:13:29.078Z",
            "fileName": "c:\\Users\\ludov\\Documents\\Code\\C++\\Utilities\\date\\source\\formatter.cpp",
            "fileType": ".cpp",
            "linesAdded": 1,
            "linesRemoved": 0,
            "projectName": "date",
            "content": {
              "added": [],
              "removed": []
            },
            "duration": 1,
            "language": "cpp"
          },
          {
            "timestamp": "2025-05-03T17:13:30.391Z",
            "fileName": "c:\\Users\\ludov\\Documents\\Code\\C++\\Utilities\\date\\source\\formatter.cpp",
            "fileType": ".cpp",
            "linesAdded": 1,
            "linesRemoved": 0,
            "projectName": "date",
            "content": {
              "added": [],
              "removed": []
            },
            "duration": 1,
            "language": "cpp"
          },
          {
            "timestamp": "2025-05-03T17:13:34.718Z",
            "fileName": "c:\\Users\\ludov\\Documents\\Code\\C++\\Utilities\\date\\source\\formatter.cpp",
            "fileType": ".cpp",
            "linesAdded": 1,
            "linesRemoved": 0,
            "projectName": "date",
            "content": {
              "added": [],
              "removed": []
            },
            "duration": 1,
            "language": "cpp"
          },
          {
            "timestamp": "2025-05-03T17:13:44.558Z",
            "fileName": "c:\\Users\\ludov\\Documents\\Code\\C++\\Utilities\\date\\source\\formatter.cpp",
            "fileType": ".cpp",
            "linesAdded": 1,
            "linesRemoved": 0,
            "projectName": "date",
            "content": {
              "added": [],
              "removed": []
            },
            "duration": 1,
            "language": "cpp"
          },
          {
            "timestamp": "2025-05-03T17:13:47.270Z",
            "fileName": "c:\\Users\\ludov\\Documents\\Code\\C++\\Utilities\\date\\source\\formatter.cpp",
            "fileType": ".cpp",
            "linesAdded": 2,
            "linesRemoved": 0,
            "projectName": "date",
            "content": {
              "added": [],
              "removed": []
            },
            "duration": 1,
            "language": "cpp"
          }
        ],
        "c:\\Users\\ludov\\Documents\\Code\\C++\\Utilities\\date\\source\\clock.cpp": [
          {
            "timestamp": "2025-05-02T22:11:38.725Z",
            "fileName": "c:\\Users\\ludov\\Documents\\Code\\C++\\Utilities\\date\\source\\clock.cpp",
            "fileType": ".cpp",
            "linesAdded": 3,
            "linesRemoved": 0,
            "projectName": "date",
            "content": {
              "added": [],
              "removed": []
            },
            "duration": 2,
            "language": "cpp"
          },
          {
            "timestamp": "2025-05-02T22:11:45.411Z",
            "fileName": "c:\\Users\\ludov\\Documents\\Code\\C++\\Utilities\\date\\source\\clock.cpp",
            "fileType": ".cpp",
            "linesAdded": 1,
            "linesRemoved": 0,
            "projectName": "date",
            "content": {
              "added": [],
              "removed": []
            },
            "duration": 1,
            "language": "cpp"
          },
          {
            "timestamp": "2025-05-02T22:11:47.156Z",
            "fileName": "c:\\Users\\ludov\\Documents\\Code\\C++\\Utilities\\date\\source\\clock.cpp",
            "fileType": ".cpp",
            "linesAdded": 2,
            "linesRemoved": 0,
            "projectName": "date",
            "content": {
              "added": [],
              "removed": []
            },
            "duration": 1,
            "language": "cpp"
          },
          {
            "timestamp": "2025-05-02T22:13:24.162Z",
            "fileName": "c:\\Users\\ludov\\Documents\\Code\\C++\\Utilities\\date\\source\\clock.cpp",
            "fileType": ".cpp",
            "linesAdded": 2,
            "linesRemoved": 0,
            "projectName": "date",
            "content": {
              "added": [],
              "removed": []
            },
            "duration": 2,
            "language": "cpp"
          },
          {
            "timestamp": "2025-05-02T22:13:32.592Z",
            "fileName": "c:\\Users\\ludov\\Documents\\Code\\C++\\Utilities\\date\\source\\clock.cpp",
            "fileType": ".cpp",
            "linesAdded": 1,
            "linesRemoved": 0,
            "projectName": "date",
            "content": {
              "added": [],
              "removed": []
            },
            "duration": 1,
            "language": "cpp"
          },
          {
            "timestamp": "2025-05-02T22:13:34.962Z",
            "fileName": "c:\\Users\\ludov\\Documents\\Code\\C++\\Utilities\\date\\source\\clock.cpp",
            "fileType": ".cpp",
            "linesAdded": 0,
            "linesRemoved": 1,
            "projectName": "date",
            "content": {
              "added": [],
              "removed": []
            },
            "duration": 1,
            "language": "cpp"
          },
          {
            "timestamp": "2025-05-02T22:13:48.789Z",
            "fileName": "c:\\Users\\ludov\\Documents\\Code\\C++\\Utilities\\date\\source\\clock.cpp",
            "fileType": ".cpp",
            "linesAdded": 1,
            "linesRemoved": 0,
            "projectName": "date",
            "content": {
              "added": [],
              "removed": []
            },
            "duration": 1,
            "language": "cpp"
          },
          {
            "timestamp": "2025-05-02T22:13:50.014Z",
            "fileName": "c:\\Users\\ludov\\Documents\\Code\\C++\\Utilities\\date\\source\\clock.cpp",
            "fileType": ".cpp",
            "linesAdded": 1,
            "linesRemoved": 0,
            "projectName": "date",
            "content": {
              "added": [],
              "removed": []
            },
            "duration": 1,
            "language": "cpp"
          },
          {
            "timestamp": "2025-05-02T22:13:52.397Z",
            "fileName": "c:\\Users\\ludov\\Documents\\Code\\C++\\Utilities\\date\\source\\clock.cpp",
            "fileType": ".cpp",
            "linesAdded": 2,
            "linesRemoved": 0,
            "projectName": "date",
            "content": {
              "added": [],
              "removed": []
            },
            "duration": 1,
            "language": "cpp"
          },
          {
            "timestamp": "2025-05-02T22:14:28.293Z",
            "fileName": "c:\\Users\\ludov\\Documents\\Code\\C++\\Utilities\\date\\source\\clock.cpp",
            "fileType": ".cpp",
            "linesAdded": 2,
            "linesRemoved": 0,
            "projectName": "date",
            "content": {
              "added": [],
              "removed": []
            },
            "duration": 1,
            "language": "cpp"
          },
          {
            "timestamp": "2025-05-02T22:14:34.807Z",
            "fileName": "c:\\Users\\ludov\\Documents\\Code\\C++\\Utilities\\date\\source\\clock.cpp",
            "fileType": ".cpp",
            "linesAdded": 1,
            "linesRemoved": 0,
            "projectName": "date",
            "content": {
              "added": [],
              "removed": []
            },
            "duration": 1,
            "language": "cpp"
          },
          {
            "timestamp": "2025-05-02T22:18:27.676Z",
            "fileName": "c:\\Users\\ludov\\Documents\\Code\\C++\\Utilities\\date\\source\\clock.cpp",
            "fileType": ".cpp",
            "linesAdded": 1,
            "linesRemoved": 0,
            "projectName": "date",
            "content": {
              "added": [],
              "removed": []
            },
            "duration": 3,
            "language": "cpp"
          },
          {
            "timestamp": "2025-05-03T13:42:37.750Z",
            "fileName": "c:\\Users\\ludov\\Documents\\Code\\C++\\Utilities\\date\\source\\clock.cpp",
            "fileType": ".cpp",
            "linesAdded": 40,
            "linesRemoved": 0,
            "projectName": "date",
            "content": {
              "added": [],
              "removed": []
            },
            "duration": 1,
            "language": "cpp"
          },
          {
            "timestamp": "2025-05-03T13:44:38.141Z",
            "fileName": "c:\\Users\\ludov\\Documents\\Code\\C++\\Utilities\\date\\source\\clock.cpp",
            "fileType": ".cpp",
            "linesAdded": 6,
            "linesRemoved": 0,
            "projectName": "date",
            "content": {
              "added": [],
              "removed": []
            },
            "duration": 2,
            "language": "cpp"
          },
          {
            "timestamp": "2025-05-03T13:44:43.772Z",
            "fileName": "c:\\Users\\ludov\\Documents\\Code\\C++\\Utilities\\date\\source\\clock.cpp",
            "fileType": ".cpp",
            "linesAdded": 5,
            "linesRemoved": 0,
            "projectName": "date",
            "content": {
              "added": [],
              "removed": []
            },
            "duration": 1,
            "language": "cpp"
          },
          {
            "timestamp": "2025-05-03T13:44:46.625Z",
            "fileName": "c:\\Users\\ludov\\Documents\\Code\\C++\\Utilities\\date\\source\\clock.cpp",
            "fileType": ".cpp",
            "linesAdded": 5,
            "linesRemoved": 0,
            "projectName": "date",
            "content": {
              "added": [],
              "removed": []
            },
            "duration": 1,
            "language": "cpp"
          },
          {
            "timestamp": "2025-05-03T13:44:49.968Z",
            "fileName": "c:\\Users\\ludov\\Documents\\Code\\C++\\Utilities\\date\\source\\clock.cpp",
            "fileType": ".cpp",
            "linesAdded": 0,
            "linesRemoved": 5,
            "projectName": "date",
            "content": {
              "added": [],
              "removed": []
            },
            "duration": 1,
            "language": "cpp"
          },
          {
            "timestamp": "2025-05-03T13:44:51.676Z",
            "fileName": "c:\\Users\\ludov\\Documents\\Code\\C++\\Utilities\\date\\source\\clock.cpp",
            "fileType": ".cpp",
            "linesAdded": 10,
            "linesRemoved": 0,
            "projectName": "date",
            "content": {
              "added": [],
              "removed": []
            },
            "duration": 1,
            "language": "cpp"
          },
          {
            "timestamp": "2025-05-03T13:44:53.708Z",
            "fileName": "c:\\Users\\ludov\\Documents\\Code\\C++\\Utilities\\date\\source\\clock.cpp",
            "fileType": ".cpp",
            "linesAdded": 5,
            "linesRemoved": 0,
            "projectName": "date",
            "content": {
              "added": [],
              "removed": []
            },
            "duration": 1,
            "language": "cpp"
          },
          {
            "timestamp": "2025-05-03T13:44:55.982Z",
            "fileName": "c:\\Users\\ludov\\Documents\\Code\\C++\\Utilities\\date\\source\\clock.cpp",
            "fileType": ".cpp",
            "linesAdded": 0,
            "linesRemoved": 1,
            "projectName": "date",
            "content": {
              "added": [],
              "removed": []
            },
            "duration": 1,
            "language": "cpp"
          },
          {
            "timestamp": "2025-05-03T13:45:32.707Z",
            "fileName": "c:\\Users\\ludov\\Documents\\Code\\C++\\Utilities\\date\\source\\clock.cpp",
            "fileType": ".cpp",
            "linesAdded": 3,
            "linesRemoved": 0,
            "projectName": "date",
            "content": {
              "added": [],
              "removed": []
            },
            "duration": 1,
            "language": "cpp"
          },
          {
            "timestamp": "2025-05-03T13:45:39.831Z",
            "fileName": "c:\\Users\\ludov\\Documents\\Code\\C++\\Utilities\\date\\source\\clock.cpp",
            "fileType": ".cpp",
            "linesAdded": 0,
            "linesRemoved": 5,
            "projectName": "date",
            "content": {
              "added": [],
              "removed": []
            },
            "duration": 1,
            "language": "cpp"
          },
          {
            "timestamp": "2025-05-03T13:45:58.909Z",
            "fileName": "c:\\Users\\ludov\\Documents\\Code\\C++\\Utilities\\date\\source\\clock.cpp",
            "fileType": ".cpp",
            "linesAdded": 1,
            "linesRemoved": 0,
            "projectName": "date",
            "content": {
              "added": [],
              "removed": []
            },
            "duration": 1,
            "language": "cpp"
          },
          {
            "timestamp": "2025-05-03T13:46:33.984Z",
            "fileName": "c:\\Users\\ludov\\Documents\\Code\\C++\\Utilities\\date\\source\\clock.cpp",
            "fileType": ".cpp",
            "linesAdded": 1,
            "linesRemoved": 0,
            "projectName": "date",
            "content": {
              "added": [],
              "removed": []
            },
            "duration": 1,
            "language": "cpp"
          },
          {
            "timestamp": "2025-05-03T13:47:36.787Z",
            "fileName": "c:\\Users\\ludov\\Documents\\Code\\C++\\Utilities\\date\\source\\clock.cpp",
            "fileType": ".cpp",
            "linesAdded": 0,
            "linesRemoved": 1,
            "projectName": "date",
            "content": {
              "added": [],
              "removed": []
            },
            "duration": 2,
            "language": "cpp"
          },
          {
            "timestamp": "2025-05-03T13:49:24.767Z",
            "fileName": "c:\\Users\\ludov\\Documents\\Code\\C++\\Utilities\\date\\source\\clock.cpp",
            "fileType": ".cpp",
            "linesAdded": 0,
            "linesRemoved": 2,
            "projectName": "date",
            "content": {
              "added": [],
              "removed": []
            },
            "duration": 1,
            "language": "cpp"
          },
          {
            "timestamp": "2025-05-03T13:49:27.363Z",
            "fileName": "c:\\Users\\ludov\\Documents\\Code\\C++\\Utilities\\date\\source\\clock.cpp",
            "fileType": ".cpp",
            "linesAdded": 3,
            "linesRemoved": 0,
            "projectName": "date",
            "content": {
              "added": [],
              "removed": []
            },
            "duration": 1,
            "language": "cpp"
          },
          {
            "timestamp": "2025-05-03T13:51:54.516Z",
            "fileName": "c:\\Users\\ludov\\Documents\\Code\\C++\\Utilities\\date\\source\\clock.cpp",
            "fileType": ".cpp",
            "linesAdded": 1,
            "linesRemoved": 0,
            "projectName": "date",
            "content": {
              "added": [],
              "removed": []
            },
            "duration": 3,
            "language": "cpp"
          },
          {
            "timestamp": "2025-05-03T13:52:08.387Z",
            "fileName": "c:\\Users\\ludov\\Documents\\Code\\C++\\Utilities\\date\\source\\clock.cpp",
            "fileType": ".cpp",
            "linesAdded": 2,
            "linesRemoved": 0,
            "projectName": "date",
            "content": {
              "added": [],
              "removed": []
            },
            "duration": 1,
            "language": "cpp"
          },
          {
            "timestamp": "2025-05-03T13:54:28.008Z",
            "fileName": "c:\\Users\\ludov\\Documents\\Code\\C++\\Utilities\\date\\source\\clock.cpp",
            "fileType": ".cpp",
            "linesAdded": 2,
            "linesRemoved": 0,
            "projectName": "date",
            "content": {
              "added": [],
              "removed": []
            },
            "duration": 1,
            "language": "cpp"
          },
          {
            "timestamp": "2025-05-03T13:54:41.339Z",
            "fileName": "c:\\Users\\ludov\\Documents\\Code\\C++\\Utilities\\date\\source\\clock.cpp",
            "fileType": ".cpp",
            "linesAdded": 1,
            "linesRemoved": 0,
            "projectName": "date",
            "content": {
              "added": [],
              "removed": []
            },
            "duration": 1,
            "language": "cpp"
          },
          {
            "timestamp": "2025-05-03T13:54:43.922Z",
            "fileName": "c:\\Users\\ludov\\Documents\\Code\\C++\\Utilities\\date\\source\\clock.cpp",
            "fileType": ".cpp",
            "linesAdded": 2,
            "linesRemoved": 0,
            "projectName": "date",
            "content": {
              "added": [],
              "removed": []
            },
            "duration": 1,
            "language": "cpp"
          },
          {
            "timestamp": "2025-05-03T13:54:48.282Z",
            "fileName": "c:\\Users\\ludov\\Documents\\Code\\C++\\Utilities\\date\\source\\clock.cpp",
            "fileType": ".cpp",
            "linesAdded": 1,
            "linesRemoved": 0,
            "projectName": "date",
            "content": {
              "added": [],
              "removed": []
            },
            "duration": 1,
            "language": "cpp"
          },
          {
            "timestamp": "2025-05-03T13:56:31.206Z",
            "fileName": "c:\\Users\\ludov\\Documents\\Code\\C++\\Utilities\\date\\source\\clock.cpp",
            "fileType": ".cpp",
            "linesAdded": 1,
            "linesRemoved": 0,
            "projectName": "date",
            "content": {
              "added": [],
              "removed": []
            },
            "duration": 1,
            "language": "cpp"
          },
          {
            "timestamp": "2025-05-03T13:56:33.452Z",
            "fileName": "c:\\Users\\ludov\\Documents\\Code\\C++\\Utilities\\date\\source\\clock.cpp",
            "fileType": ".cpp",
            "linesAdded": 2,
            "linesRemoved": 0,
            "projectName": "date",
            "content": {
              "added": [],
              "removed": []
            },
            "duration": 1,
            "language": "cpp"
          },
          {
            "timestamp": "2025-05-03T13:56:50.950Z",
            "fileName": "c:\\Users\\ludov\\Documents\\Code\\C++\\Utilities\\date\\source\\clock.cpp",
            "fileType": ".cpp",
            "linesAdded": 3,
            "linesRemoved": 0,
            "projectName": "date",
            "content": {
              "added": [],
              "removed": []
            },
            "duration": 1,
            "language": "cpp"
          },
          {
            "timestamp": "2025-05-03T13:57:09.364Z",
            "fileName": "c:\\Users\\ludov\\Documents\\Code\\C++\\Utilities\\date\\source\\clock.cpp",
            "fileType": ".cpp",
            "linesAdded": 0,
            "linesRemoved": 3,
            "projectName": "date",
            "content": {
              "added": [],
              "removed": []
            },
            "duration": 1,
            "language": "cpp"
          },
          {
            "timestamp": "2025-05-03T14:06:46.935Z",
            "fileName": "c:\\Users\\ludov\\Documents\\Code\\C++\\Utilities\\date\\source\\clock.cpp",
            "fileType": ".cpp",
            "linesAdded": 0,
            "linesRemoved": 3,
            "projectName": "date",
            "content": {
              "added": [],
              "removed": []
            },
            "duration": 3,
            "language": "cpp"
          },
          {
            "timestamp": "2025-05-03T14:07:40.619Z",
            "fileName": "c:\\Users\\ludov\\Documents\\Code\\C++\\Utilities\\date\\source\\clock.cpp",
            "fileType": ".cpp",
            "linesAdded": 1,
            "linesRemoved": 0,
            "projectName": "date",
            "content": {
              "added": [],
              "removed": []
            },
            "duration": 1,
            "language": "cpp"
          },
          {
            "timestamp": "2025-05-03T14:07:43.083Z",
            "fileName": "c:\\Users\\ludov\\Documents\\Code\\C++\\Utilities\\date\\source\\clock.cpp",
            "fileType": ".cpp",
            "linesAdded": 2,
            "linesRemoved": 0,
            "projectName": "date",
            "content": {
              "added": [],
              "removed": []
            },
            "duration": 1,
            "language": "cpp"
          },
          {
            "timestamp": "2025-05-03T14:08:13.501Z",
            "fileName": "c:\\Users\\ludov\\Documents\\Code\\C++\\Utilities\\date\\source\\clock.cpp",
            "fileType": ".cpp",
            "linesAdded": 1,
            "linesRemoved": 0,
            "projectName": "date",
            "content": {
              "added": [],
              "removed": []
            },
            "duration": 1,
            "language": "cpp"
          },
          {
            "timestamp": "2025-05-03T14:08:22.247Z",
            "fileName": "c:\\Users\\ludov\\Documents\\Code\\C++\\Utilities\\date\\source\\clock.cpp",
            "fileType": ".cpp",
            "linesAdded": 1,
            "linesRemoved": 0,
            "projectName": "date",
            "content": {
              "added": [],
              "removed": []
            },
            "duration": 1,
            "language": "cpp"
          },
          {
            "timestamp": "2025-05-03T14:08:32.354Z",
            "fileName": "c:\\Users\\ludov\\Documents\\Code\\C++\\Utilities\\date\\source\\clock.cpp",
            "fileType": ".cpp",
            "linesAdded": 1,
            "linesRemoved": 0,
            "projectName": "date",
            "content": {
              "added": [],
              "removed": []
            },
            "duration": 1,
            "language": "cpp"
          },
          {
            "timestamp": "2025-05-03T14:09:32.839Z",
            "fileName": "c:\\Users\\ludov\\Documents\\Code\\C++\\Utilities\\date\\source\\clock.cpp",
            "fileType": ".cpp",
            "linesAdded": 0,
            "linesRemoved": 4,
            "projectName": "date",
            "content": {
              "added": [],
              "removed": []
            },
            "duration": 2,
            "language": "cpp"
          },
          {
            "timestamp": "2025-05-03T14:09:34.285Z",
            "fileName": "c:\\Users\\ludov\\Documents\\Code\\C++\\Utilities\\date\\source\\clock.cpp",
            "fileType": ".cpp",
            "linesAdded": 0,
            "linesRemoved": 1,
            "projectName": "date",
            "content": {
              "added": [],
              "removed": []
            },
            "duration": 1,
            "language": "cpp"
          },
          {
            "timestamp": "2025-05-03T14:09:36.333Z",
            "fileName": "c:\\Users\\ludov\\Documents\\Code\\C++\\Utilities\\date\\source\\clock.cpp",
            "fileType": ".cpp",
            "linesAdded": 0,
            "linesRemoved": 1,
            "projectName": "date",
            "content": {
              "added": [],
              "removed": []
            },
            "duration": 1,
            "language": "cpp"
          },
          {
            "timestamp": "2025-05-03T14:24:54.234Z",
            "fileName": "c:\\Users\\ludov\\Documents\\Code\\C++\\Utilities\\date\\source\\clock.cpp",
            "fileType": ".cpp",
            "linesAdded": 25,
            "linesRemoved": 0,
            "projectName": "date",
            "content": {
              "added": [],
              "removed": []
            },
            "duration": 1,
            "language": "cpp"
          }
        ],
        "c:\\Users\\ludov\\Documents\\Code\\C++\\Utilities\\date\\.vscode\\launch.json": [
          {
            "timestamp": "2025-05-03T13:57:24.640Z",
            "fileName": "c:\\Users\\ludov\\Documents\\Code\\C++\\Utilities\\date\\.vscode\\launch.json",
            "fileType": ".json",
            "linesAdded": 17,
            "linesRemoved": 0,
            "projectName": "date",
            "content": {
              "added": [],
              "removed": []
            },
            "duration": 1,
            "language": "json"
          },
          {
            "timestamp": "2025-05-03T17:07:07.145Z",
            "fileName": "c:\\Users\\ludov\\Documents\\Code\\C++\\Utilities\\date\\.vscode\\launch.json",
            "fileType": ".json",
            "linesAdded": 17,
            "linesRemoved": 0,
            "projectName": "date",
            "content": {
              "added": [],
              "removed": []
            },
            "duration": 1,
            "language": "json"
          }
        ]
      },
      "languageStats": {
        "hpp": 9,
        "cpp": 8
      },
      "changeFrequency": {
        "0": 10,
        "23": 7
      },
      "topFiles": [
        "c:\\Users\\ludov\\Documents\\Code\\C++\\Utilities\\date\\source\\printer.cpp",
        "c:\\Users\\ludov\\Documents\\Code\\C++\\Utilities\\date\\include\\printer.hpp",
        "c:\\Users\\ludov\\Documents\\Code\\C++\\Utilities\\date\\include\\day.hpp",
        "c:\\Users\\ludov\\Documents\\Code\\C++\\Utilities\\date\\include\\month.hpp",
        "c:\\Users\\ludov\\Documents\\Code\\C++\\Utilities\\date\\source\\main.cpp"
      ],
      "averageChangeSize": 13.6
    }
  },
  "totalActiveTime": 17,
  "totalProjects": 1,
  "totalFiles": 5,
  "mostActiveHours": [
    0,
    23
  ],
  "mostUsedLanguages": [
    "hpp",
    "cpp"
  ]
}