{
  "date": "2025-04-21",
  "projects": {
    "cp": {
      "totalLinesAdded": 78,
      "totalLinesRemoved": 0,
      "totalActiveTime": 4,
      "files": {
        "c:\\Users\\ludov\\Documents\\Code\\C++\\Utilities\\cp\\.gitignore": [
          {
            "timestamp": "2025-04-20T22:03:40.793Z",
            "fileName": "c:\\Users\\ludov\\Documents\\Code\\C++\\Utilities\\cp\\.gitignore",
            "fileType": "unknown",
            "linesAdded": 46,
            "linesRemoved": 0,
            "projectName": "cp",
            "content": {
              "added": [],
              "removed": []
            },
            "duration": 0,
            "language": "unknown"
          },
          {
            "timestamp": "2025-04-20T22:03:42.311Z",
            "fileName": "c:\\Users\\ludov\\Documents\\Code\\C++\\Utilities\\cp\\.gitignore",
            "fileType": "unknown",
            "linesAdded": 1,
            "linesRemoved": 0,
            "projectName": "cp",
            "content": {
              "added": [],
              "removed": []
            },
            "duration": 1,
            "language": "unknown"
          },
          {
            "timestamp": "2025-04-20T22:03:45.149Z",
            "fileName": "c:\\Users\\ludov\\Documents\\Code\\C++\\Utilities\\cp\\.gitignore",
            "fileType": "unknown",
            "linesAdded": 1,
            "linesRemoved": 0,
            "projectName": "cp",
            "content": {
              "added": [],
              "removed": []
            },
            "duration": 1,
            "language": "unknown"
          }
        ],
        "c:\\Users\\ludov\\Documents\\Code\\C++\\Utilities\\cp\\CMakeLists.txt": [
          {
            "timestamp": "2025-04-20T22:04:00.124Z",
            "fileName": "c:\\Users\\ludov\\Documents\\Code\\C++\\Utilities\\cp\\CMakeLists.txt",
            "fileType": ".txt",
            "linesAdded": 13,
            "linesRemoved": 0,
            "projectName": "cp",
            "content": {
              "added": [],
              "removed": []
            },
            "duration": 1,
            "language": "txt"
          }
        ],
        "c:\\Users\\ludov\\Documents\\Code\\C++\\Utilities\\cp\\.vscode\\launch.json": [
          {
            "timestamp": "2025-04-20T22:04:21.854Z",
            "fileName": "c:\\Users\\ludov\\Documents\\Code\\C++\\Utilities\\cp\\.vscode\\launch.json",
            "fileType": ".json",
            "linesAdded": 17,
            "linesRemoved": 0,
            "projectName": "cp",
            "content": {
              "added": [],
              "removed": []
            },
            "duration": 1,
            "language": "json"
          }
        ]
      },
      "languageStats": {
        "unknown": 2,
        "txt": 1,
        "json": 1
      },
      "changeFrequency": {
        "0": 4
      },
      "topFiles": [
        "c:\\Users\\ludov\\Documents\\Code\\C++\\Utilities\\cp\\.gitignore",
        "c:\\Users\\ludov\\Documents\\Code\\C++\\Utilities\\cp\\CMakeLists.txt",
        "c:\\Users\\ludov\\Documents\\Code\\C++\\Utilities\\cp\\.vscode\\launch.json"
      ],
      "averageChangeSize": 15.6
    },
    "echo": {
      "totalLinesAdded": 989,
      "totalLinesRemoved": 119,
      "totalActiveTime": 120,
      "files": {
        "c:\\Users\\ludov\\Documents\\Code\\C++\\Utilities\\echo\\source\\Parser.cpp": [
          {
            "timestamp": "2025-04-21T16:43:55.703Z",
            "fileName": "c:\\Users\\ludov\\Documents\\Code\\C++\\Utilities\\echo\\source\\Parser.cpp",
            "fileType": ".cpp",
            "linesAdded": 117,
            "linesRemoved": 0,
            "projectName": "echo",
            "content": {
              "added": [],
              "removed": []
            },
            "duration": 0,
            "language": "cpp"
          },
          {
            "timestamp": "2025-04-21T16:51:06.178Z",
            "fileName": "c:\\Users\\ludov\\Documents\\Code\\C++\\Utilities\\echo\\source\\Parser.cpp",
            "fileType": ".cpp",
            "linesAdded": 0,
            "linesRemoved": 5,
            "projectName": "echo",
            "content": {
              "added": [],
              "removed": []
            },
            "duration": 4,
            "language": "cpp"
          },
          {
            "timestamp": "2025-04-21T16:51:09.597Z",
            "fileName": "c:\\Users\\ludov\\Documents\\Code\\C++\\Utilities\\echo\\source\\Parser.cpp",
            "fileType": ".cpp",
            "linesAdded": 0,
            "linesRemoved": 1,
            "projectName": "echo",
            "content": {
              "added": [],
              "removed": []
            },
            "duration": 1,
            "language": "cpp"
          },
          {
            "timestamp": "2025-04-21T16:51:18.243Z",
            "fileName": "c:\\Users\\ludov\\Documents\\Code\\C++\\Utilities\\echo\\source\\Parser.cpp",
            "fileType": ".cpp",
            "linesAdded": 1,
            "linesRemoved": 0,
            "projectName": "echo",
            "content": {
              "added": [],
              "removed": []
            },
            "duration": 1,
            "language": "cpp"
          },
          {
            "timestamp": "2025-04-21T16:51:19.668Z",
            "fileName": "c:\\Users\\ludov\\Documents\\Code\\C++\\Utilities\\echo\\source\\Parser.cpp",
            "fileType": ".cpp",
            "linesAdded": 5,
            "linesRemoved": 0,
            "projectName": "echo",
            "content": {
              "added": [],
              "removed": []
            },
            "duration": 1,
            "language": "cpp"
          },
          {
            "timestamp": "2025-04-21T16:51:26.981Z",
            "fileName": "c:\\Users\\ludov\\Documents\\Code\\C++\\Utilities\\echo\\source\\Parser.cpp",
            "fileType": ".cpp",
            "linesAdded": 0,
            "linesRemoved": 6,
            "projectName": "echo",
            "content": {
              "added": [],
              "removed": []
            },
            "duration": 1,
            "language": "cpp"
          },
          {
            "timestamp": "2025-04-21T16:51:29.921Z",
            "fileName": "c:\\Users\\ludov\\Documents\\Code\\C++\\Utilities\\echo\\source\\Parser.cpp",
            "fileType": ".cpp",
            "linesAdded": 6,
            "linesRemoved": 0,
            "projectName": "echo",
            "content": {
              "added": [],
              "removed": []
            },
            "duration": 1,
            "language": "cpp"
          },
          {
            "timestamp": "2025-04-21T16:51:34.053Z",
            "fileName": "c:\\Users\\ludov\\Documents\\Code\\C++\\Utilities\\echo\\source\\Parser.cpp",
            "fileType": ".cpp",
            "linesAdded": 0,
            "linesRemoved": 3,
            "projectName": "echo",
            "content": {
              "added": [],
              "removed": []
            },
            "duration": 1,
            "language": "cpp"
          },
          {
            "timestamp": "2025-04-21T16:51:35.289Z",
            "fileName": "c:\\Users\\ludov\\Documents\\Code\\C++\\Utilities\\echo\\source\\Parser.cpp",
            "fileType": ".cpp",
            "linesAdded": 0,
            "linesRemoved": 1,
            "projectName": "echo",
            "content": {
              "added": [],
              "removed": []
            },
            "duration": 1,
            "language": "cpp"
          },
          {
            "timestamp": "2025-04-21T16:51:41.322Z",
            "fileName": "c:\\Users\\ludov\\Documents\\Code\\C++\\Utilities\\echo\\source\\Parser.cpp",
            "fileType": ".cpp",
            "linesAdded": 4,
            "linesRemoved": 0,
            "projectName": "echo",
            "content": {
              "added": [],
              "removed": []
            },
            "duration": 1,
            "language": "cpp"
          },
          {
            "timestamp": "2025-04-21T16:52:07.709Z",
            "fileName": "c:\\Users\\ludov\\Documents\\Code\\C++\\Utilities\\echo\\source\\Parser.cpp",
            "fileType": ".cpp",
            "linesAdded": 0,
            "linesRemoved": 5,
            "projectName": "echo",
            "content": {
              "added": [],
              "removed": []
            },
            "duration": 1,
            "language": "cpp"
          },
          {
            "timestamp": "2025-04-21T16:52:16.381Z",
            "fileName": "c:\\Users\\ludov\\Documents\\Code\\C++\\Utilities\\echo\\source\\Parser.cpp",
            "fileType": ".cpp",
            "linesAdded": 0,
            "linesRemoved": 8,
            "projectName": "echo",
            "content": {
              "added": [],
              "removed": []
            },
            "duration": 1,
            "language": "cpp"
          },
          {
            "timestamp": "2025-04-21T16:52:19.241Z",
            "fileName": "c:\\Users\\ludov\\Documents\\Code\\C++\\Utilities\\echo\\source\\Parser.cpp",
            "fileType": ".cpp",
            "linesAdded": 0,
            "linesRemoved": 4,
            "projectName": "echo",
            "content": {
              "added": [],
              "removed": []
            },
            "duration": 1,
            "language": "cpp"
          },
          {
            "timestamp": "2025-04-21T16:52:24.114Z",
            "fileName": "c:\\Users\\ludov\\Documents\\Code\\C++\\Utilities\\echo\\source\\Parser.cpp",
            "fileType": ".cpp",
            "linesAdded": 4,
            "linesRemoved": 0,
            "projectName": "echo",
            "content": {
              "added": [],
              "removed": []
            },
            "duration": 1,
            "language": "cpp"
          },
          {
            "timestamp": "2025-04-21T16:52:32.504Z",
            "fileName": "c:\\Users\\ludov\\Documents\\Code\\C++\\Utilities\\echo\\source\\Parser.cpp",
            "fileType": ".cpp",
            "linesAdded": 9,
            "linesRemoved": 0,
            "projectName": "echo",
            "content": {
              "added": [],
              "removed": []
            },
            "duration": 1,
            "language": "cpp"
          },
          {
            "timestamp": "2025-04-21T16:52:38.087Z",
            "fileName": "c:\\Users\\ludov\\Documents\\Code\\C++\\Utilities\\echo\\source\\Parser.cpp",
            "fileType": ".cpp",
            "linesAdded": 0,
            "linesRemoved": 9,
            "projectName": "echo",
            "content": {
              "added": [],
              "removed": []
            },
            "duration": 1,
            "language": "cpp"
          },
          {
            "timestamp": "2025-04-21T16:52:40.679Z",
            "fileName": "c:\\Users\\ludov\\Documents\\Code\\C++\\Utilities\\echo\\source\\Parser.cpp",
            "fileType": ".cpp",
            "linesAdded": 9,
            "linesRemoved": 0,
            "projectName": "echo",
            "content": {
              "added": [],
              "removed": []
            },
            "duration": 1,
            "language": "cpp"
          },
          {
            "timestamp": "2025-04-21T16:55:07.438Z",
            "fileName": "c:\\Users\\ludov\\Documents\\Code\\C++\\Utilities\\echo\\source\\Parser.cpp",
            "fileType": ".cpp",
            "linesAdded": 0,
            "linesRemoved": 1,
            "projectName": "echo",
            "content": {
              "added": [],
              "removed": []
            },
            "duration": 3,
            "language": "cpp"
          },
          {
            "timestamp": "2025-04-21T17:00:13.518Z",
            "fileName": "c:\\Users\\ludov\\Documents\\Code\\C++\\Utilities\\echo\\source\\Parser.cpp",
            "fileType": ".cpp",
            "linesAdded": 0,
            "linesRemoved": 4,
            "projectName": "echo",
            "content": {
              "added": [],
              "removed": []
            },
            "duration": 0,
            "language": "cpp"
          },
          {
            "timestamp": "2025-04-21T17:00:17.752Z",
            "fileName": "c:\\Users\\ludov\\Documents\\Code\\C++\\Utilities\\echo\\source\\Parser.cpp",
            "fileType": ".cpp",
            "linesAdded": 0,
            "linesRemoved": 5,
            "projectName": "echo",
            "content": {
              "added": [],
              "removed": []
            },
            "duration": 1,
            "language": "cpp"
          },
          {
            "timestamp": "2025-04-21T17:00:19.987Z",
            "fileName": "c:\\Users\\ludov\\Documents\\Code\\C++\\Utilities\\echo\\source\\Parser.cpp",
            "fileType": ".cpp",
            "linesAdded": 1,
            "linesRemoved": 0,
            "projectName": "echo",
            "content": {
              "added": [],
              "removed": []
            },
            "duration": 1,
            "language": "cpp"
          },
          {
            "timestamp": "2025-04-21T17:00:26.034Z",
            "fileName": "c:\\Users\\ludov\\Documents\\Code\\C++\\Utilities\\echo\\source\\Parser.cpp",
            "fileType": ".cpp",
            "linesAdded": 0,
            "linesRemoved": 12,
            "projectName": "echo",
            "content": {
              "added": [],
              "removed": []
            },
            "duration": 1,
            "language": "cpp"
          },
          {
            "timestamp": "2025-04-21T17:00:34.155Z",
            "fileName": "c:\\Users\\ludov\\Documents\\Code\\C++\\Utilities\\echo\\source\\Parser.cpp",
            "fileType": ".cpp",
            "linesAdded": 0,
            "linesRemoved": 9,
            "projectName": "echo",
            "content": {
              "added": [],
              "removed": []
            },
            "duration": 1,
            "language": "cpp"
          },
          {
            "timestamp": "2025-04-21T17:00:41.879Z",
            "fileName": "c:\\Users\\ludov\\Documents\\Code\\C++\\Utilities\\echo\\source\\Parser.cpp",
            "fileType": ".cpp",
            "linesAdded": 0,
            "linesRemoved": 7,
            "projectName": "echo",
            "content": {
              "added": [],
              "removed": []
            },
            "duration": 1,
            "language": "cpp"
          },
          {
            "timestamp": "2025-04-21T17:01:13.986Z",
            "fileName": "c:\\Users\\ludov\\Documents\\Code\\C++\\Utilities\\echo\\source\\Parser.cpp",
            "fileType": ".cpp",
            "linesAdded": 0,
            "linesRemoved": 5,
            "projectName": "echo",
            "content": {
              "added": [],
              "removed": []
            },
            "duration": 1,
            "language": "cpp"
          },
          {
            "timestamp": "2025-04-21T17:01:24.851Z",
            "fileName": "c:\\Users\\ludov\\Documents\\Code\\C++\\Utilities\\echo\\source\\Parser.cpp",
            "fileType": ".cpp",
            "linesAdded": 1,
            "linesRemoved": 0,
            "projectName": "echo",
            "content": {
              "added": [],
              "removed": []
            },
            "duration": 1,
            "language": "cpp"
          },
          {
            "timestamp": "2025-04-21T17:01:36.975Z",
            "fileName": "c:\\Users\\ludov\\Documents\\Code\\C++\\Utilities\\echo\\source\\Parser.cpp",
            "fileType": ".cpp",
            "linesAdded": 1,
            "linesRemoved": 0,
            "projectName": "echo",
            "content": {
              "added": [],
              "removed": []
            },
            "duration": 1,
            "language": "cpp"
          },
          {
            "timestamp": "2025-04-21T17:15:55.939Z",
            "fileName": "c:\\Users\\ludov\\Documents\\Code\\C++\\Utilities\\echo\\source\\Parser.cpp",
            "fileType": ".cpp",
            "linesAdded": 73,
            "linesRemoved": 0,
            "projectName": "echo",
            "content": {
              "added": [],
              "removed": []
            },
            "duration": 1,
            "language": "cpp"
          },
          {
            "timestamp": "2025-04-21T17:21:11.025Z",
            "fileName": "c:\\Users\\ludov\\Documents\\Code\\C++\\Utilities\\echo\\source\\Parser.cpp",
            "fileType": ".cpp",
            "linesAdded": 0,
            "linesRemoved": 9,
            "projectName": "echo",
            "content": {
              "added": [],
              "removed": []
            },
            "duration": 2,
            "language": "cpp"
          },
          {
            "timestamp": "2025-04-21T17:27:23.604Z",
            "fileName": "c:\\Users\\ludov\\Documents\\Code\\C++\\Utilities\\echo\\source\\Parser.cpp",
            "fileType": ".cpp",
            "linesAdded": 0,
            "linesRemoved": 2,
            "projectName": "echo",
            "content": {
              "added": [],
              "removed": []
            },
            "duration": 0,
            "language": "cpp"
          },
          {
            "timestamp": "2025-04-21T17:34:19.585Z",
            "fileName": "c:\\Users\\ludov\\Documents\\Code\\C++\\Utilities\\echo\\source\\Parser.cpp",
            "fileType": ".cpp",
            "linesAdded": 1,
            "linesRemoved": 0,
            "projectName": "echo",
            "content": {
              "added": [],
              "removed": []
            },
            "duration": 0,
            "language": "cpp"
          },
          {
            "timestamp": "2025-04-21T17:34:29.680Z",
            "fileName": "c:\\Users\\ludov\\Documents\\Code\\C++\\Utilities\\echo\\source\\Parser.cpp",
            "fileType": ".cpp",
            "linesAdded": 1,
            "linesRemoved": 0,
            "projectName": "echo",
            "content": {
              "added": [],
              "removed": []
            },
            "duration": 1,
            "language": "cpp"
          },
          {
            "timestamp": "2025-04-21T17:36:10.567Z",
            "fileName": "c:\\Users\\ludov\\Documents\\Code\\C++\\Utilities\\echo\\source\\Parser.cpp",
            "fileType": ".cpp",
            "linesAdded": 2,
            "linesRemoved": 0,
            "projectName": "echo",
            "content": {
              "added": [],
              "removed": []
            },
            "duration": 1,
            "language": "cpp"
          },
          {
            "timestamp": "2025-04-21T17:36:45.432Z",
            "fileName": "c:\\Users\\ludov\\Documents\\Code\\C++\\Utilities\\echo\\source\\Parser.cpp",
            "fileType": ".cpp",
            "linesAdded": 1,
            "linesRemoved": 0,
            "projectName": "echo",
            "content": {
              "added": [],
              "removed": []
            },
            "duration": 1,
            "language": "cpp"
          },
          {
            "timestamp": "2025-04-21T17:36:47.232Z",
            "fileName": "c:\\Users\\ludov\\Documents\\Code\\C++\\Utilities\\echo\\source\\Parser.cpp",
            "fileType": ".cpp",
            "linesAdded": 2,
            "linesRemoved": 0,
            "projectName": "echo",
            "content": {
              "added": [],
              "removed": []
            },
            "duration": 1,
            "language": "cpp"
          },
          {
            "timestamp": "2025-04-21T17:37:09.463Z",
            "fileName": "c:\\Users\\ludov\\Documents\\Code\\C++\\Utilities\\echo\\source\\Parser.cpp",
            "fileType": ".cpp",
            "linesAdded": 1,
            "linesRemoved": 0,
            "projectName": "echo",
            "content": {
              "added": [],
              "removed": []
            },
            "duration": 1,
            "language": "cpp"
          },
          {
            "timestamp": "2025-04-21T17:37:10.768Z",
            "fileName": "c:\\Users\\ludov\\Documents\\Code\\C++\\Utilities\\echo\\source\\Parser.cpp",
            "fileType": ".cpp",
            "linesAdded": 1,
            "linesRemoved": 0,
            "projectName": "echo",
            "content": {
              "added": [],
              "removed": []
            },
            "duration": 1,
            "language": "cpp"
          },
          {
            "timestamp": "2025-04-21T17:39:47.260Z",
            "fileName": "c:\\Users\\ludov\\Documents\\Code\\C++\\Utilities\\echo\\source\\Parser.cpp",
            "fileType": ".cpp",
            "linesAdded": 1,
            "linesRemoved": 0,
            "projectName": "echo",
            "content": {
              "added": [],
              "removed": []
            },
            "duration": 3,
            "language": "cpp"
          },
          {
            "timestamp": "2025-04-21T20:11:28.463Z",
            "fileName": "c:\\Users\\ludov\\Documents\\Code\\C++\\Utilities\\echo\\source\\Parser.cpp",
            "fileType": ".cpp",
            "linesAdded": 72,
            "linesRemoved": 0,
            "projectName": "echo",
            "content": {
              "added": [],
              "removed": []
            },
            "duration": 0,
            "language": "cpp"
          },
          {
            "timestamp": "2025-04-21T20:11:57.845Z",
            "fileName": "c:\\Users\\ludov\\Documents\\Code\\C++\\Utilities\\echo\\source\\Parser.cpp",
            "fileType": ".cpp",
            "linesAdded": 2,
            "linesRemoved": 0,
            "projectName": "echo",
            "content": {
              "added": [],
              "removed": []
            },
            "duration": 1,
            "language": "cpp"
          },
          {
            "timestamp": "2025-04-21T20:12:53.202Z",
            "fileName": "c:\\Users\\ludov\\Documents\\Code\\C++\\Utilities\\echo\\source\\Parser.cpp",
            "fileType": ".cpp",
            "linesAdded": 1,
            "linesRemoved": 0,
            "projectName": "echo",
            "content": {
              "added": [],
              "removed": []
            },
            "duration": 1,
            "language": "cpp"
          },
          {
            "timestamp": "2025-04-21T20:15:04.565Z",
            "fileName": "c:\\Users\\ludov\\Documents\\Code\\C++\\Utilities\\echo\\source\\Parser.cpp",
            "fileType": ".cpp",
            "linesAdded": 1,
            "linesRemoved": 0,
            "projectName": "echo",
            "content": {
              "added": [],
              "removed": []
            },
            "duration": 3,
            "language": "cpp"
          },
          {
            "timestamp": "2025-04-21T20:15:35.400Z",
            "fileName": "c:\\Users\\ludov\\Documents\\Code\\C++\\Utilities\\echo\\source\\Parser.cpp",
            "fileType": ".cpp",
            "linesAdded": 1,
            "linesRemoved": 0,
            "projectName": "echo",
            "content": {
              "added": [],
              "removed": []
            },
            "duration": 1,
            "language": "cpp"
          },
          {
            "timestamp": "2025-04-21T20:16:46.625Z",
            "fileName": "c:\\Users\\ludov\\Documents\\Code\\C++\\Utilities\\echo\\source\\Parser.cpp",
            "fileType": ".cpp",
            "linesAdded": 2,
            "linesRemoved": 0,
            "projectName": "echo",
            "content": {
              "added": [],
              "removed": []
            },
            "duration": 2,
            "language": "cpp"
          },
          {
            "timestamp": "2025-04-21T20:18:55.286Z",
            "fileName": "c:\\Users\\ludov\\Documents\\Code\\C++\\Utilities\\echo\\source\\Parser.cpp",
            "fileType": ".cpp",
            "linesAdded": 2,
            "linesRemoved": 0,
            "projectName": "echo",
            "content": {
              "added": [],
              "removed": []
            },
            "duration": 3,
            "language": "cpp"
          },
          {
            "timestamp": "2025-04-21T20:20:18.910Z",
            "fileName": "c:\\Users\\ludov\\Documents\\Code\\C++\\Utilities\\echo\\source\\Parser.cpp",
            "fileType": ".cpp",
            "linesAdded": 1,
            "linesRemoved": 0,
            "projectName": "echo",
            "content": {
              "added": [],
              "removed": []
            },
            "duration": 2,
            "language": "cpp"
          },
          {
            "timestamp": "2025-04-21T20:22:17.562Z",
            "fileName": "c:\\Users\\ludov\\Documents\\Code\\C++\\Utilities\\echo\\source\\Parser.cpp",
            "fileType": ".cpp",
            "linesAdded": 0,
            "linesRemoved": 1,
            "projectName": "echo",
            "content": {
              "added": [],
              "removed": []
            },
            "duration": 2,
            "language": "cpp"
          },
          {
            "timestamp": "2025-04-21T20:25:50.949Z",
            "fileName": "c:\\Users\\ludov\\Documents\\Code\\C++\\Utilities\\echo\\source\\Parser.cpp",
            "fileType": ".cpp",
            "linesAdded": 1,
            "linesRemoved": 0,
            "projectName": "echo",
            "content": {
              "added": [],
              "removed": []
            },
            "duration": 4,
            "language": "cpp"
          },
          {
            "timestamp": "2025-04-21T20:26:40.379Z",
            "fileName": "c:\\Users\\ludov\\Documents\\Code\\C++\\Utilities\\echo\\source\\Parser.cpp",
            "fileType": ".cpp",
            "linesAdded": 0,
            "linesRemoved": 1,
            "projectName": "echo",
            "content": {
              "added": [],
              "removed": []
            },
            "duration": 1,
            "language": "cpp"
          },
          {
            "timestamp": "2025-04-21T20:36:00.602Z",
            "fileName": "c:\\Users\\ludov\\Documents\\Code\\C++\\Utilities\\echo\\source\\Parser.cpp",
            "fileType": ".cpp",
            "linesAdded": 4,
            "linesRemoved": 0,
            "projectName": "echo",
            "content": {
              "added": [],
              "removed": []
            },
            "duration": 1,
            "language": "cpp"
          },
          {
            "timestamp": "2025-04-21T20:36:19.860Z",
            "fileName": "c:\\Users\\ludov\\Documents\\Code\\C++\\Utilities\\echo\\source\\Parser.cpp",
            "fileType": ".cpp",
            "linesAdded": 0,
            "linesRemoved": 4,
            "projectName": "echo",
            "content": {
              "added": [],
              "removed": []
            },
            "duration": 1,
            "language": "cpp"
          },
          {
            "timestamp": "2025-04-21T21:13:18.563Z",
            "fileName": "c:\\Users\\ludov\\Documents\\Code\\C++\\Utilities\\echo\\source\\Parser.cpp",
            "fileType": ".cpp",
            "linesAdded": 79,
            "linesRemoved": 0,
            "projectName": "echo",
            "content": {
              "added": [],
              "removed": []
            },
            "duration": 1,
            "language": "cpp"
          },
          {
            "timestamp": "2025-04-21T21:14:32.441Z",
            "fileName": "c:\\Users\\ludov\\Documents\\Code\\C++\\Utilities\\echo\\source\\Parser.cpp",
            "fileType": ".cpp",
            "linesAdded": 4,
            "linesRemoved": 0,
            "projectName": "echo",
            "content": {
              "added": [],
              "removed": []
            },
            "duration": 2,
            "language": "cpp"
          },
          {
            "timestamp": "2025-04-21T21:16:16.967Z",
            "fileName": "c:\\Users\\ludov\\Documents\\Code\\C++\\Utilities\\echo\\source\\Parser.cpp",
            "fileType": ".cpp",
            "linesAdded": 2,
            "linesRemoved": 0,
            "projectName": "echo",
            "content": {
              "added": [],
              "removed": []
            },
            "duration": 2,
            "language": "cpp"
          },
          {
            "timestamp": "2025-04-21T21:16:23.201Z",
            "fileName": "c:\\Users\\ludov\\Documents\\Code\\C++\\Utilities\\echo\\source\\Parser.cpp",
            "fileType": ".cpp",
            "linesAdded": 1,
            "linesRemoved": 0,
            "projectName": "echo",
            "content": {
              "added": [],
              "removed": []
            },
            "duration": 1,
            "language": "cpp"
          },
          {
            "timestamp": "2025-04-21T21:18:45.272Z",
            "fileName": "c:\\Users\\ludov\\Documents\\Code\\C++\\Utilities\\echo\\source\\Parser.cpp",
            "fileType": ".cpp",
            "linesAdded": 1,
            "linesRemoved": 0,
            "projectName": "echo",
            "content": {
              "added": [],
              "removed": []
            },
            "duration": 3,
            "language": "cpp"
          },
          {
            "timestamp": "2025-04-21T21:19:01.155Z",
            "fileName": "c:\\Users\\ludov\\Documents\\Code\\C++\\Utilities\\echo\\source\\Parser.cpp",
            "fileType": ".cpp",
            "linesAdded": 1,
            "linesRemoved": 0,
            "projectName": "echo",
            "content": {
              "added": [],
              "removed": []
            },
            "duration": 1,
            "language": "cpp"
          },
          {
            "timestamp": "2025-04-21T21:19:12.449Z",
            "fileName": "c:\\Users\\ludov\\Documents\\Code\\C++\\Utilities\\echo\\source\\Parser.cpp",
            "fileType": ".cpp",
            "linesAdded": 1,
            "linesRemoved": 0,
            "projectName": "echo",
            "content": {
              "added": [],
              "removed": []
            },
            "duration": 1,
            "language": "cpp"
          },
          {
            "timestamp": "2025-04-21T21:19:18.232Z",
            "fileName": "c:\\Users\\ludov\\Documents\\Code\\C++\\Utilities\\echo\\source\\Parser.cpp",
            "fileType": ".cpp",
            "linesAdded": 2,
            "linesRemoved": 0,
            "projectName": "echo",
            "content": {
              "added": [],
              "removed": []
            },
            "duration": 1,
            "language": "cpp"
          },
          {
            "timestamp": "2025-04-21T21:19:34.338Z",
            "fileName": "c:\\Users\\ludov\\Documents\\Code\\C++\\Utilities\\echo\\source\\Parser.cpp",
            "fileType": ".cpp",
            "linesAdded": 0,
            "linesRemoved": 2,
            "projectName": "echo",
            "content": {
              "added": [],
              "removed": []
            },
            "duration": 1,
            "language": "cpp"
          },
          {
            "timestamp": "2025-04-21T21:19:51.991Z",
            "fileName": "c:\\Users\\ludov\\Documents\\Code\\C++\\Utilities\\echo\\source\\Parser.cpp",
            "fileType": ".cpp",
            "linesAdded": 2,
            "linesRemoved": 0,
            "projectName": "echo",
            "content": {
              "added": [],
              "removed": []
            },
            "duration": 1,
            "language": "cpp"
          },
          {
            "timestamp": "2025-04-21T21:19:53.315Z",
            "fileName": "c:\\Users\\ludov\\Documents\\Code\\C++\\Utilities\\echo\\source\\Parser.cpp",
            "fileType": ".cpp",
            "linesAdded": 0,
            "linesRemoved": 1,
            "projectName": "echo",
            "content": {
              "added": [],
              "removed": []
            },
            "duration": 1,
            "language": "cpp"
          }
        ],
        "c:\\Users\\ludov\\Documents\\Code\\C++\\Utilities\\echo\\.vscode\\launch.json": [
          {
            "timestamp": "2025-04-21T16:44:33.041Z",
            "fileName": "c:\\Users\\ludov\\Documents\\Code\\C++\\Utilities\\echo\\.vscode\\launch.json",
            "fileType": ".json",
            "linesAdded": 16,
            "linesRemoved": 0,
            "projectName": "echo",
            "content": {
              "added": [],
              "removed": []
            },
            "duration": 1,
            "language": "json"
          },
          {
            "timestamp": "2025-04-21T17:19:23.170Z",
            "fileName": "c:\\Users\\ludov\\Documents\\Code\\C++\\Utilities\\echo\\.vscode\\launch.json",
            "fileType": ".json",
            "linesAdded": 16,
            "linesRemoved": 0,
            "projectName": "echo",
            "content": {
              "added": [],
              "removed": []
            },
            "duration": 4,
            "language": "json"
          },
          {
            "timestamp": "2025-04-21T20:28:40.311Z",
            "fileName": "c:\\Users\\ludov\\Documents\\Code\\C++\\Utilities\\echo\\.vscode\\launch.json",
            "fileType": ".json",
            "linesAdded": 16,
            "linesRemoved": 0,
            "projectName": "echo",
            "content": {
              "added": [],
              "removed": []
            },
            "duration": 2,
            "language": "json"
          },
          {
            "timestamp": "2025-04-21T20:28:41.320Z",
            "fileName": "c:\\Users\\ludov\\Documents\\Code\\C++\\Utilities\\echo\\.vscode\\launch.json",
            "fileType": ".json",
            "linesAdded": 1,
            "linesRemoved": 0,
            "projectName": "echo",
            "content": {
              "added": [],
              "removed": []
            },
            "duration": 1,
            "language": "json"
          },
          {
            "timestamp": "2025-04-21T20:28:54.557Z",
            "fileName": "c:\\Users\\ludov\\Documents\\Code\\C++\\Utilities\\echo\\.vscode\\launch.json",
            "fileType": ".json",
            "linesAdded": 0,
            "linesRemoved": 1,
            "projectName": "echo",
            "content": {
              "added": [],
              "removed": []
            },
            "duration": 1,
            "language": "json"
          },
          {
            "timestamp": "2025-04-21T21:20:05.405Z",
            "fileName": "c:\\Users\\ludov\\Documents\\Code\\C++\\Utilities\\echo\\.vscode\\launch.json",
            "fileType": ".json",
            "linesAdded": 16,
            "linesRemoved": 0,
            "projectName": "echo",
            "content": {
              "added": [],
              "removed": []
            },
            "duration": 1,
            "language": "json"
          }
        ],
        "c:\\Users\\ludov\\Documents\\Code\\C++\\Utilities\\echo\\include\\Parser.hpp": [
          {
            "timestamp": "2025-04-21T16:45:10.441Z",
            "fileName": "c:\\Users\\ludov\\Documents\\Code\\C++\\Utilities\\echo\\include\\Parser.hpp",
            "fileType": ".hpp",
            "linesAdded": 47,
            "linesRemoved": 0,
            "projectName": "echo",
            "content": {
              "added": [],
              "removed": []
            },
            "duration": 1,
            "language": "hpp"
          },
          {
            "timestamp": "2025-04-21T17:35:17.326Z",
            "fileName": "c:\\Users\\ludov\\Documents\\Code\\C++\\Utilities\\echo\\include\\Parser.hpp",
            "fileType": ".hpp",
            "linesAdded": 47,
            "linesRemoved": 0,
            "projectName": "echo",
            "content": {
              "added": [],
              "removed": []
            },
            "duration": 1,
            "language": "hpp"
          },
          {
            "timestamp": "2025-04-21T17:35:20.642Z",
            "fileName": "c:\\Users\\ludov\\Documents\\Code\\C++\\Utilities\\echo\\include\\Parser.hpp",
            "fileType": ".hpp",
            "linesAdded": 2,
            "linesRemoved": 0,
            "projectName": "echo",
            "content": {
              "added": [],
              "removed": []
            },
            "duration": 1,
            "language": "hpp"
          },
          {
            "timestamp": "2025-04-21T17:41:47.789Z",
            "fileName": "c:\\Users\\ludov\\Documents\\Code\\C++\\Utilities\\echo\\include\\Parser.hpp",
            "fileType": ".hpp",
            "linesAdded": 0,
            "linesRemoved": 1,
            "projectName": "echo",
            "content": {
              "added": [],
              "removed": []
            },
            "duration": 3,
            "language": "hpp"
          },
          {
            "timestamp": "2025-04-21T17:41:52.672Z",
            "fileName": "c:\\Users\\ludov\\Documents\\Code\\C++\\Utilities\\echo\\include\\Parser.hpp",
            "fileType": ".hpp",
            "linesAdded": 1,
            "linesRemoved": 0,
            "projectName": "echo",
            "content": {
              "added": [],
              "removed": []
            },
            "duration": 1,
            "language": "hpp"
          },
          {
            "timestamp": "2025-04-21T20:27:35.457Z",
            "fileName": "c:\\Users\\ludov\\Documents\\Code\\C++\\Utilities\\echo\\include\\Parser.hpp",
            "fileType": ".hpp",
            "linesAdded": 49,
            "linesRemoved": 0,
            "projectName": "echo",
            "content": {
              "added": [],
              "removed": []
            },
            "duration": 1,
            "language": "hpp"
          },
          {
            "timestamp": "2025-04-21T20:27:36.495Z",
            "fileName": "c:\\Users\\ludov\\Documents\\Code\\C++\\Utilities\\echo\\include\\Parser.hpp",
            "fileType": ".hpp",
            "linesAdded": 11,
            "linesRemoved": 0,
            "projectName": "echo",
            "content": {
              "added": [],
              "removed": []
            },
            "duration": 1,
            "language": "hpp"
          },
          {
            "timestamp": "2025-04-21T20:35:03.636Z",
            "fileName": "c:\\Users\\ludov\\Documents\\Code\\C++\\Utilities\\echo\\include\\Parser.hpp",
            "fileType": ".hpp",
            "linesAdded": 1,
            "linesRemoved": 0,
            "projectName": "echo",
            "content": {
              "added": [],
              "removed": []
            },
            "duration": 0,
            "language": "hpp"
          },
          {
            "timestamp": "2025-04-21T20:35:06.234Z",
            "fileName": "c:\\Users\\ludov\\Documents\\Code\\C++\\Utilities\\echo\\include\\Parser.hpp",
            "fileType": ".hpp",
            "linesAdded": 3,
            "linesRemoved": 0,
            "projectName": "echo",
            "content": {
              "added": [],
              "removed": []
            },
            "duration": 1,
            "language": "hpp"
          },
          {
            "timestamp": "2025-04-21T20:35:22.010Z",
            "fileName": "c:\\Users\\ludov\\Documents\\Code\\C++\\Utilities\\echo\\include\\Parser.hpp",
            "fileType": ".hpp",
            "linesAdded": 0,
            "linesRemoved": 4,
            "projectName": "echo",
            "content": {
              "added": [],
              "removed": []
            },
            "duration": 1,
            "language": "hpp"
          },
          {
            "timestamp": "2025-04-21T20:36:00.586Z",
            "fileName": "c:\\Users\\ludov\\Documents\\Code\\C++\\Utilities\\echo\\include\\Parser.hpp",
            "fileType": ".hpp",
            "linesAdded": 1,
            "linesRemoved": 0,
            "projectName": "echo",
            "content": {
              "added": [],
              "removed": []
            },
            "duration": 1,
            "language": "hpp"
          },
          {
            "timestamp": "2025-04-21T20:36:19.845Z",
            "fileName": "c:\\Users\\ludov\\Documents\\Code\\C++\\Utilities\\echo\\include\\Parser.hpp",
            "fileType": ".hpp",
            "linesAdded": 0,
            "linesRemoved": 1,
            "projectName": "echo",
            "content": {
              "added": [],
              "removed": []
            },
            "duration": 1,
            "language": "hpp"
          },
          {
            "timestamp": "2025-04-21T21:13:06.382Z",
            "fileName": "c:\\Users\\ludov\\Documents\\Code\\C++\\Utilities\\echo\\include\\Parser.hpp",
            "fileType": ".hpp",
            "linesAdded": 61,
            "linesRemoved": 0,
            "projectName": "echo",
            "content": {
              "added": [],
              "removed": []
            },
            "duration": 0,
            "language": "hpp"
          },
          {
            "timestamp": "2025-04-21T21:13:12.355Z",
            "fileName": "c:\\Users\\ludov\\Documents\\Code\\C++\\Utilities\\echo\\include\\Parser.hpp",
            "fileType": ".hpp",
            "linesAdded": 1,
            "linesRemoved": 0,
            "projectName": "echo",
            "content": {
              "added": [],
              "removed": []
            },
            "duration": 1,
            "language": "hpp"
          },
          {
            "timestamp": "2025-04-21T21:14:32.425Z",
            "fileName": "c:\\Users\\ludov\\Documents\\Code\\C++\\Utilities\\echo\\include\\Parser.hpp",
            "fileType": ".hpp",
            "linesAdded": 1,
            "linesRemoved": 0,
            "projectName": "echo",
            "content": {
              "added": [],
              "removed": []
            },
            "duration": 2,
            "language": "hpp"
          }
        ],
        "c:\\Users\\ludov\\Documents\\Code\\C++\\Utilities\\echo\\source\\main.cpp": [
          {
            "timestamp": "2025-04-21T16:45:20.935Z",
            "fileName": "c:\\Users\\ludov\\Documents\\Code\\C++\\Utilities\\echo\\source\\main.cpp",
            "fileType": ".cpp",
            "linesAdded": 68,
            "linesRemoved": 0,
            "projectName": "echo",
            "content": {
              "added": [],
              "removed": []
            },
            "duration": 1,
            "language": "cpp"
          },
          {
            "timestamp": "2025-04-21T16:47:13.243Z",
            "fileName": "c:\\Users\\ludov\\Documents\\Code\\C++\\Utilities\\echo\\source\\main.cpp",
            "fileType": ".cpp",
            "linesAdded": 1,
            "linesRemoved": 0,
            "projectName": "echo",
            "content": {
              "added": [],
              "removed": []
            },
            "duration": 2,
            "language": "cpp"
          },
          {
            "timestamp": "2025-04-21T16:47:25.192Z",
            "fileName": "c:\\Users\\ludov\\Documents\\Code\\C++\\Utilities\\echo\\source\\main.cpp",
            "fileType": ".cpp",
            "linesAdded": 0,
            "linesRemoved": 1,
            "projectName": "echo",
            "content": {
              "added": [],
              "removed": []
            },
            "duration": 1,
            "language": "cpp"
          },
          {
            "timestamp": "2025-04-21T21:20:40.571Z",
            "fileName": "c:\\Users\\ludov\\Documents\\Code\\C++\\Utilities\\echo\\source\\main.cpp",
            "fileType": ".cpp",
            "linesAdded": 68,
            "linesRemoved": 0,
            "projectName": "echo",
            "content": {
              "added": [],
              "removed": []
            },
            "duration": 1,
            "language": "cpp"
          },
          {
            "timestamp": "2025-04-21T21:20:43.200Z",
            "fileName": "c:\\Users\\ludov\\Documents\\Code\\C++\\Utilities\\echo\\source\\main.cpp",
            "fileType": ".cpp",
            "linesAdded": 1,
            "linesRemoved": 0,
            "projectName": "echo",
            "content": {
              "added": [],
              "removed": []
            },
            "duration": 1,
            "language": "cpp"
          }
        ],
        "c:\\Users\\ludov\\Documents\\Code\\C++\\Utilities\\echo\\test\\testParser.cpp": [
          {
            "timestamp": "2025-04-21T16:45:45.035Z",
            "fileName": "c:\\Users\\ludov\\Documents\\Code\\C++\\Utilities\\echo\\test\\testParser.cpp",
            "fileType": ".cpp",
            "linesAdded": 45,
            "linesRemoved": 0,
            "projectName": "echo",
            "content": {
              "added": [],
              "removed": []
            },
            "duration": 1,
            "language": "cpp"
          },
          {
            "timestamp": "2025-04-21T17:14:46.070Z",
            "fileName": "c:\\Users\\ludov\\Documents\\Code\\C++\\Utilities\\echo\\test\\testParser.cpp",
            "fileType": ".cpp",
            "linesAdded": 45,
            "linesRemoved": 0,
            "projectName": "echo",
            "content": {
              "added": [],
              "removed": []
            },
            "duration": 0,
            "language": "cpp"
          }
        ],
        "c:\\Users\\ludov\\Documents\\Code\\C++\\Utilities\\echo\\CMakeLists.txt": [
          {
            "timestamp": "2025-04-21T17:14:58.264Z",
            "fileName": "c:\\Users\\ludov\\Documents\\Code\\C++\\Utilities\\echo\\CMakeLists.txt",
            "fileType": ".txt",
            "linesAdded": 44,
            "linesRemoved": 0,
            "projectName": "echo",
            "content": {
              "added": [],
              "removed": []
            },
            "duration": 1,
            "language": "txt"
          },
          {
            "timestamp": "2025-04-21T17:28:33.004Z",
            "fileName": "c:\\Users\\ludov\\Documents\\Code\\C++\\Utilities\\echo\\CMakeLists.txt",
            "fileType": ".txt",
            "linesAdded": 0,
            "linesRemoved": 3,
            "projectName": "echo",
            "content": {
              "added": [],
              "removed": []
            },
            "duration": 2,
            "language": "txt"
          },
          {
            "timestamp": "2025-04-21T17:28:44.767Z",
            "fileName": "c:\\Users\\ludov\\Documents\\Code\\C++\\Utilities\\echo\\CMakeLists.txt",
            "fileType": ".txt",
            "linesAdded": 3,
            "linesRemoved": 0,
            "projectName": "echo",
            "content": {
              "added": [],
              "removed": []
            },
            "duration": 1,
            "language": "txt"
          },
          {
            "timestamp": "2025-04-21T17:28:49.572Z",
            "fileName": "c:\\Users\\ludov\\Documents\\Code\\C++\\Utilities\\echo\\CMakeLists.txt",
            "fileType": ".txt",
            "linesAdded": 0,
            "linesRemoved": 1,
            "projectName": "echo",
            "content": {
              "added": [],
              "removed": []
            },
            "duration": 1,
            "language": "txt"
          },
          {
            "timestamp": "2025-04-21T17:28:51.479Z",
            "fileName": "c:\\Users\\ludov\\Documents\\Code\\C++\\Utilities\\echo\\CMakeLists.txt",
            "fileType": ".txt",
            "linesAdded": 0,
            "linesRemoved": 2,
            "projectName": "echo",
            "content": {
              "added": [],
              "removed": []
            },
            "duration": 1,
            "language": "txt"
          },
          {
            "timestamp": "2025-04-21T17:29:02.872Z",
            "fileName": "c:\\Users\\ludov\\Documents\\Code\\C++\\Utilities\\echo\\CMakeLists.txt",
            "fileType": ".txt",
            "linesAdded": 2,
            "linesRemoved": 0,
            "projectName": "echo",
            "content": {
              "added": [],
              "removed": []
            },
            "duration": 1,
            "language": "txt"
          },
          {
            "timestamp": "2025-04-21T17:29:04.167Z",
            "fileName": "c:\\Users\\ludov\\Documents\\Code\\C++\\Utilities\\echo\\CMakeLists.txt",
            "fileType": ".txt",
            "linesAdded": 1,
            "linesRemoved": 0,
            "projectName": "echo",
            "content": {
              "added": [],
              "removed": []
            },
            "duration": 1,
            "language": "txt"
          }
        ]
      },
      "languageStats": {
        "cpp": 5,
        "json": 1,
        "hpp": 1
      },
      "changeFrequency": {
        "18": 7
      },
      "topFiles": [
        "c:\\Users\\ludov\\Documents\\Code\\C++\\Utilities\\echo\\source\\main.cpp",
        "c:\\Users\\ludov\\Documents\\Code\\C++\\Utilities\\echo\\source\\Parser.cpp",
        "c:\\Users\\ludov\\Documents\\Code\\C++\\Utilities\\echo\\.vscode\\launch.json",
        "c:\\Users\\ludov\\Documents\\Code\\C++\\Utilities\\echo\\include\\Parser.hpp",
        "c:\\Users\\ludov\\Documents\\Code\\C++\\Utilities\\echo\\test\\testParser.cpp"
      ],
      "averageChangeSize": 42.142857142857146
    }
  },
  "totalActiveTime": 4,
  "totalProjects": 1,
  "totalFiles": 3,
  "mostActiveHours": [
    0
  ],
  "mostUsedLanguages": [
    "unknown",
    "txt",
    "json"
  ]
}